Workbook
Name SuppliesUsed: 'Inputs'!$B$5
Name InsuranceExpired: 'Inputs'!$B$6
Name DepreciationExpense: 'Inputs'!$B$7
Name WagesAccrued: 'Inputs'!$B$8
Name RevenueEarned: 'Inputs'!$B$9
Name SelectedPeriod: 'Control Panel'!$B$3

Sheet Inputs
A1: TechStart Month-End Adjustment Inputs
A2: Enter or select the period amounts. Yellow cells are inputs.
A4: Input | B4: Amount | C4: Maximum | D4: Validation
A5: Supplies used | B5: 1200 | C5: 5500
A6: Insurance expired | B6: 300 | C6: 1200
A7: Depreciation expense | B7: 400 | C7: 2000
A8: Wages accrued | B8: 1800 | C8: 4000
A9: Revenue earned | B9: 1200 | C9: 1200

Sheet Close Model
A1: TechStart Month-End Close Model
A3: Adjustment Account | B3: Debit | C3: Credit
A4: Supplies Expense | B4: =SuppliesUsed | C4: 0
A5: Supplies | B5: 0 | C5: =SuppliesUsed
A6: Insurance Expense | B6: =InsuranceExpired | C6: 0
A7: Prepaid Insurance | B7: 0 | C7: =InsuranceExpired
A8: Depreciation Expense | B8: =DepreciationExpense | C8: 0
A9: Accumulated Depreciation | B9: 0 | C9: =DepreciationExpense
A10: Wages Expense | B10: =WagesAccrued | C10: 0
A11: Wages Payable | B11: 0 | C11: =WagesAccrued
A12: Unearned Revenue | B12: =RevenueEarned | C12: 0
A13: Service Revenue | B13: 0 | C13: =RevenueEarned
A14: Adjustment totals | B14: =SUM(B4:B13) | C14: =SUM(C4:C13)
A15: Adjustment difference | B15: =B14-C14
A18: Account | B18: Unadjusted Debit | C18: Unadjusted Credit | D18: Adjustment Debit | E18: Adjustment Credit | F18: Adjusted Debit | G18: Adjusted Credit
A19: Cash | B19: 9000 | C19: 0 | D19: 0 | E19: 0 | F19: =MAX((B19+D19)-(C19+E19),0) | G19: =MAX((C19+E19)-(B19+D19),0)
A20: Accounts Receivable | B20: 4000 | C20: 0 | D20: 0 | E20: 0 | F20: =MAX((B20+D20)-(C20+E20),0) | G20: =MAX((C20+E20)-(B20+D20),0)
A21: Supplies | B21: 5500 | C21: 0 | D21: 0 | E21: =SuppliesUsed | F21: =MAX((B21+D21)-(C21+E21),0) | G21: =MAX((C21+E21)-(B21+D21),0)
A22: Prepaid Insurance | B22: 1200 | C22: 0 | D22: 0 | E22: =InsuranceExpired | F22: =MAX((B22+D22)-(C22+E22),0) | G22: =MAX((C22+E22)-(B22+D22),0)
A23: Equipment | B23: 32000 | C23: 0 | D23: 0 | E23: 0 | F23: =MAX((B23+D23)-(C23+E23),0) | G23: =MAX((C23+E23)-(B23+D23),0)
A24: Accumulated Depreciation | B24: 0 | C24: 0 | D24: 0 | E24: =DepreciationExpense | F24: =MAX((B24+D24)-(C24+E24),0) | G24: =MAX((C24+E24)-(B24+D24),0)
A25: Accounts Payable | B25: 0 | C25: 6000 | D25: 0 | E25: 0 | F25: =MAX((B25+D25)-(C25+E25),0) | G25: =MAX((C25+E25)-(B25+D25),0)
A26: Wages Payable | B26: 0 | C26: 0 | D26: 0 | E26: =WagesAccrued | F26: =MAX((B26+D26)-(C26+E26),0) | G26: =MAX((C26+E26)-(B26+D26),0)
A27: Unearned Revenue | B27: 0 | C27: 1200 | D27: =RevenueEarned | E27: 0 | F27: =MAX((B27+D27)-(C27+E27),0) | G27: =MAX((C27+E27)-(B27+D27),0)
A28: Owner Capital | B28: 0 | C28: 30000 | D28: 0 | E28: 0 | F28: =MAX((B28+D28)-(C28+E28),0) | G28: =MAX((C28+E28)-(B28+D28),0)
A29: Service Revenue | B29: 0 | C29: 14500 | D29: 0 | E29: =RevenueEarned | F29: =MAX((B29+D29)-(C29+E29),0) | G29: =MAX((C29+E29)-(B29+D29),0)
A30: Supplies Expense | B30: 0 | C30: 0 | D30: =SuppliesUsed | E30: 0 | F30: =MAX((B30+D30)-(C30+E30),0) | G30: =MAX((C30+E30)-(B30+D30),0)
A31: Insurance Expense | B31: 0 | C31: 0 | D31: =InsuranceExpired | E31: 0 | F31: =MAX((B31+D31)-(C31+E31),0) | G31: =MAX((C31+E31)-(B31+D31),0)
A32: Depreciation Expense | B32: 0 | C32: 0 | D32: =DepreciationExpense | E32: 0 | F32: =MAX((B32+D32)-(C32+E32),0) | G32: =MAX((C32+E32)-(B32+D32),0)
A33: Wages Expense | B33: 0 | C33: 0 | D33: =WagesAccrued | E33: 0 | F33: =MAX((B33+D33)-(C33+E33),0) | G33: =MAX((C33+E33)-(B33+D33),0)
A34: Adjusted trial balance totals | F34: =SUM(F19:F33) | G34: =SUM(G19:G33)
A35: Adjusted trial balance difference | F35: =F34-G34

Sheet Control Panel
A1: Month-End Close Control Panel
A3: Selected period | B3: March
A4: Total adjustment debits | B4: ='Close Model'!B14
A5: Total adjustment credits | B5: ='Close Model'!C14
A6: Adjustment difference | B6: ='Close Model'!B15
A7: Adjusted trial balance difference | B7: ='Close Model'!F35
A8: Failed validation checks | B8: 0
A9: CloseStatus | B9: =IF(OR(COUNT('Close Model'!B4:C13)<>20,COUNT('Close Model'!F19:G33)<>30),"Not finished",IF(AND(B6=0,B7=0,B8=0),"Complete","Review flagged items"))
