Workbook

Sheet Asset Register
A1: Asset Register
A3: Asset ID | B3: Description | C3: Cost | D3: Useful Life | E3: Salvage Value | F3: Method | G3: Purchase Date | H3: Depreciable Base
A4: A001 | B4: Espresso Machine - La Marzocco KB90 | C4: 12500 | D4: 7 | E4: 1500 | F4: SL | G4: 2025-01-15 | H4: =C4-E4
A5: A002 | B5: Espresso Machine - La Marzocco KB90 | C5: 12500 | D5: 7 | E5: 1500 | F5: SL | G5: 2025-02-01 | H5: =C5-E5
A6: A003 | B6: Espresso Machine - La Marzocco Linea Mini | C6: 6500 | D6: 7 | E6: 800 | F6: SL | G6: 2025-03-10 | H6: =C6-E6
A7: A004 | B7: Refrigerated Display Case - 6ft | C7: 4200 | D7: 10 | E7: 500 | F7: SL | G7: 2025-01-20 | H7: =C7-E7
A8: A005 | B8: Refrigerated Display Case - 6ft | C8: 4200 | D8: 10 | E8: 500 | F8: SL | G8: 2025-02-05 | H8: =C8-E8
A9: A006 | B9: Commercial Convection Oven - Dual | C9: 8800 | D9: 12 | E9: 1000 | F9: SL | G9: 2025-01-25 | H9: =C9-E9
A10: A007 | B10: Square POS System Bundle | C10: 3200 | D10: 4 | E10: 400 | F10: DDB | G10: 2025-02-10 | H10: =C10-E10
A11: A008 | B11: Square POS System Bundle | C11: 3200 | D11: 4 | E11: 400 | F11: DDB | G11: 2025-02-15 | H11: =C11-E11
A12: A009 | B12: Commercial Refrigerator - Reach-In | C12: 5500 | D12: 10 | E12: 600 | F12: SL | G12: 2025-01-30 | H12: =C12-E12
A13: A010 | B13: Commercial Refrigerator - Reach-In | C13: 5500 | D13: 10 | E13: 600 | F13: SL | G13: 2025-02-08 | H13: =C13-E13
A14: A011 | B14: Espresso Grinder - Mahlkönig EK43 | C14: 3800 | D14: 7 | E14: 500 | F14: SL | G14: 2025-01-15 | H14: =C14-E14
A15: A012 | B15: Espresso Grinder - Mahlkönig EK43 | C15: 3800 | D15: 7 | E15: 500 | F15: SL | G15: 2025-02-01 | H15: =C15-E15
... A18: A015 | B18: Outdoor Seating - Weatherproof Set | C18: 3500 | D18: 5 | E18: 300 | F18: SL | G18: 2025-03-01 | H18: =C18-E18

Sheet Depreciation Schedule
A1: Depreciation Schedule
A2: Selected Asset ID | B2: ='Asset Register'!A4 | D2: Cost | E2: ='Asset Register'!C4
D3: Useful Life | E3: ='Asset Register'!D4
D4: Salvage | E4: ='Asset Register'!E4
A6: Year | B6: Beginning BV | C6: Depreciation Expense | D6: Accumulated Depreciation | E6: Ending BV | F6: Check | G6: Method
A7: 1 | B7: ='Asset Register'!C4 | C7: =IF('Asset Register'!F4="DDB",MIN(B7*2/'Asset Register'!D4,B7-'Asset Register'!E4),('Asset Register'!C4-'Asset Register'!E4)/'Asset Register'!D4) | D7: =C7 | E7: =B7-C7 | F7: =IF(E7=('Asset Register'!C4-D7),"OK","ERROR") | G7: ='Asset Register'!F4
A8: 2 | B8: =E7 | C8: =IF('Asset Register'!F4="DDB",MIN(B8*2/'Asset Register'!D4,B8-'Asset Register'!E4),('Asset Register'!C4-'Asset Register'!E4)/'Asset Register'!D4) | D8: =D7+C8 | E8: =B8-C8 | F8: =IF(E8=('Asset Register'!C4-D8),"OK","ERROR") | G8: ='Asset Register'!F4
A9: 3 | B9: =E8 | C9: =IF('Asset Register'!F4="DDB",MIN(B9*2/'Asset Register'!D4,B9-'Asset Register'!E4),('Asset Register'!C4-'Asset Register'!E4)/'Asset Register'!D4) | D9: =D8+C9 | E9: =B9-C9 | F9: =IF(E9=('Asset Register'!C4-D9),"OK","ERROR") | G9: ='Asset Register'!F4
A10: 4 | B10: =E9 | C10: =IF('Asset Register'!F4="DDB",MIN(B10*2/'Asset Register'!D4,B10-'Asset Register'!E4),('Asset Register'!C4-'Asset Register'!E4)/'Asset Register'!D4) | D10: =D9+C10 | E10: =B10-C10 | F10: =IF(E10=('Asset Register'!C4-D10),"OK","ERROR") | G10: ='Asset Register'!F4
A11: 5 | B11: =E10 | C11: =IF('Asset Register'!F4="DDB",MIN(B11*2/'Asset Register'!D4,B11-'Asset Register'!E4),('Asset Register'!C4-'Asset Register'!E4)/'Asset Register'!D4) | D11: =D10+C11 | E11: =B11-C11 | F11: =IF(E11=('Asset Register'!C4-D11),"OK","ERROR") | G11: ='Asset Register'!F4
A12: 6 | B12: =E11 | C12: =IF('Asset Register'!F4="DDB",MIN(B12*2/'Asset Register'!D4,B12-'Asset Register'!E4),('Asset Register'!C4-'Asset Register'!E4)/'Asset Register'!D4) | D12: =D11+C12 | E12: =B12-C12 | F12: =IF(E12=('Asset Register'!C4-D12),"OK","ERROR") | G12: ='Asset Register'!F4
A13: 7 | B13: =E12 | C13: =IF('Asset Register'!F4="DDB",MIN(B13*2/'Asset Register'!D4,B13-'Asset Register'!E4),('Asset Register'!C4-'Asset Register'!E4)/'Asset Register'!D4) | D13: =D12+C13 | E13: =B13-C13 | F13: =IF(E13=('Asset Register'!C4-D13),"OK","ERROR") | G13: ='Asset Register'!F4
A14: 8 | B14: =E13 | C14: =IF('Asset Register'!F4="DDB",MIN(B14*2/'Asset Register'!D4,B14-'Asset Register'!E4),('Asset Register'!C4-'Asset Register'!E4)/'Asset Register'!D4) | D14: =D13+C14 | E14: =B14-C14 | F14: =IF(E14=('Asset Register'!C4-D14),"OK","ERROR") | G14: ='Asset Register'!F4

Sheet Method Comparison
A1: Method Comparison
A3: Year | B3: SL Expense | C3: DDB Expense | D3: SL Ending BV | E3: DDB Ending BV | F3: Difference (Expense)
A4: 1 | B4: =('Asset Register'!C4-'Asset Register'!E4)/'Asset Register'!D4 | C4: =MIN('Asset Register'!C4*2/'Asset Register'!D4,'Asset Register'!C4-'Asset Register'!E4) | D4: ='Asset Register'!C4-B4 | E4: ='Asset Register'!C4-C4 | F4: =B4-C4
A5: =A4+1 | B5: =B4 | C5: =MIN(E4*2/'Asset Register'!D4,E4-'Asset Register'!E4) | D5: =D4-B5 | E5: =E4-C5 | F5: =B5-C5
A6: =A5+1 | B6: =B4 | C6: =MIN(E5*2/'Asset Register'!D4,E5-'Asset Register'!E4) | D6: =D5-B6 | E6: =E5-C6 | F6: =B6-C6
A7: =A6+1 | B7: =B4 | C7: =MIN(E6*2/'Asset Register'!D4,E6-'Asset Register'!E4) | D7: =D6-B7 | E7: =E6-C7 | F7: =B7-C7
A8: =A7+1 | B8: =B4 | C8: =MIN(E7*2/'Asset Register'!D4,E7-'Asset Register'!E4) | D8: =D7-B8 | E8: =E7-C8 | F8: =B8-C8
A9: =A8+1 | B9: =B4 | C9: =MIN(E8*2/'Asset Register'!D4,E8-'Asset Register'!E4) | D9: =D8-B9 | E9: =E8-C9 | F9: =B9-C9

Sheet Recommendation
A1: Recommendation
A3: Claim: | B3: Use SL or DDB based on expense timing and business needs.
A4: Evidence 1 (cell reference): | B4: Example: 'Method Comparison'!B4
A5: Evidence 2 (cell reference):
A6: Evidence 3 (cell reference):
A7: Risk / Limitation:
A8: Final Recommendation:
