Workbook

Sheet Entry Categories
A1: Entry Categories
A3: Entry ID | B3: Business Entry | C3: Amount | D3: Report | E3: Section | F3: Statement Line | G3: Reason
A4: E-001 | B4: Product Sales Revenue | C4: 95000 | D4: Income Statement | E4: Revenue | F4: Sales Revenue | G4: Earned from product sales.
A5: E-002 | B5: Service Revenue | C5: 12000 | D5: Income Statement | E5: Revenue | F5: Service Revenue | G5: Earned from customer service work.
A6: E-003 | B6: Direct Product Costs | C6: 38000 | D6: Income Statement | E6: Direct Costs | F6: Cost of Goods Sold | G6: Costs tied directly to products sold.
A7: E-004 | B7: Payroll Expense | C7: 17000 | D7: Income Statement | E7: Operating Expenses | F7: Payroll Expense | G7: Staff wages for the period.
A8: E-005 | B8: Rent Expense | C8: 7200 | D8: Income Statement | E8: Operating Expenses | F8: Rent Expense | G8: Workspace rent for the period.
A9: E-006 | B9: Utilities Expense | C9: 2900 | D9: Income Statement | E9: Operating Expenses | F9: Utilities Expense | G9: Electricity, internet, and water.
A10: E-007 | B10: Insurance Expense | C10: 1800 | D10: Income Statement | E10: Operating Expenses | F10: Insurance Expense | G10: Insurance used during the year.
A11: E-008 | B11: Advertising Expense | C11: 3500 | D11: Income Statement | E11: Operating Expenses | F11: Advertising Expense | G11: Promotion for the period.
A12: E-009 | B12: Interest on Bank Loan | C12: 1600 | D12: Income Statement | E12: Other Expense | F12: Interest Expense | G12: Cost of borrowing.
A13: E-010 | B13: Cash in Bank | C13: 24500 | D13: Balance Sheet | E13: Current Assets | F13: Cash | G13: Cash still owned at year-end.
A14: E-011 | B14: Accounts Receivable | C14: 9700 | D14: Balance Sheet | E14: Current Assets | F14: Accounts Receivable | G14: Customers owe this amount.
A15: E-012 | B15: Inventory | C15: 14300 | D15: Balance Sheet | E15: Current Assets | F15: Inventory | G15: Products still on hand.
... A19: E-016 | B19: Owner Capital | C19: 30900 | D19: Balance Sheet | E19: Equity | F19: Owner Capital | G19: Owner investment in the company.
A20: E-017 | B20: Fixed Assets at Cost | C20: =SUM(AssetData[Cost]) | D20: Balance Sheet | E20: Fixed Assets | F20: Fixed Assets at Cost | G20: Linked from the asset register.

Sheet Asset Register
A1: Asset Register
A3: Asset ID | B3: Description | C3: Cost | D3: Salvage Value | E3: Useful Life | F3: Purchase Date | G3: Months in Service | H3: Depreciable Base | I3: Asset Class
A4: A-001 | B4: Delivery Van | C4: 30000 | D4: 5000 | E4: 5 | F4: 2025-04-01 | G4: 9 | H4: =C4-D4
A5: A-002 | B5: POS & Laptop Package | C5: 12000 | D5: 2000 | E5: 4 | F5: 2025-07-01 | G5: 6 | H5: =C5-D5
A6: A-003 | B6: Server & Security System | C6: 8000 | D6: 800 | E6: 3 | F6: 2025-10-01 | G6: 3 | H6: =C6-D6
A7: A-004 | B7: Workshop Equipment | C7: 18000 | D7: 3000 | E7: 6 | F7: 2025-03-01 | G7: 10 | H7: =C7-D7

Sheet Partial-Year Depreciation
A1: Partial-Year Depreciation
A3: Asset ID | B3: Description | C3: Cost | D3: Salvage | E3: Life | F3: Months | G3: SLN Full-Year | H3: DDB Full-Year | I3: SL Year 1 | J3: DDB Year 1 | K3: SL End BV | L3: DDB End BV
A4: A-001 | B4: =XLOOKUP(A4,AssetData[Asset ID],AssetData[Description]) | C4: =XLOOKUP(A4,AssetData[Asset ID],AssetData[Cost]) | D4: =XLOOKUP(A4,AssetData[Asset ID],AssetData[Salvage Value]) | E4: =XLOOKUP(A4,AssetData[Asset ID],AssetData[Useful Life]) | F4: =XLOOKUP(A4,AssetData[Asset ID],AssetData[Months in Service]) | G4: =SLN(C4,D4,E4) | H4: =DDB(C4,D4,E4,1) | I4: =G4*F4/12 | J4: =H4*F4/12 | K4: =C4-I4 | L4: =C4-J4
A5: A-002 | B5: =XLOOKUP(A5,AssetData[Asset ID],AssetData[Description]) | C5: =XLOOKUP(A5,AssetData[Asset ID],AssetData[Cost]) | D5: =XLOOKUP(A5,AssetData[Asset ID],AssetData[Salvage Value]) | E5: =XLOOKUP(A5,AssetData[Asset ID],AssetData[Useful Life]) | F5: =XLOOKUP(A5,AssetData[Asset ID],AssetData[Months in Service]) | G5: =SLN(C5,D5,E5) | H5: =DDB(C5,D5,E5,1) | I5: =G5*F5/12 | J5: =H5*F5/12 | K5: =C5-I5 | L5: =C5-J5
A6: A-003 | B6: =XLOOKUP(A6,AssetData[Asset ID],AssetData[Description]) | C6: =XLOOKUP(A6,AssetData[Asset ID],AssetData[Cost]) | D6: =XLOOKUP(A6,AssetData[Asset ID],AssetData[Salvage Value]) | E6: =XLOOKUP(A6,AssetData[Asset ID],AssetData[Useful Life]) | F6: =XLOOKUP(A6,AssetData[Asset ID],AssetData[Months in Service]) | G6: =SLN(C6,D6,E6) | H6: =DDB(C6,D6,E6,1) | I6: =G6*F6/12 | J6: =H6*F6/12 | K6: =C6-I6 | L6: =C6-J6
A7: A-004 | B7: =XLOOKUP(A7,AssetData[Asset ID],AssetData[Description]) | C7: =XLOOKUP(A7,AssetData[Asset ID],AssetData[Cost]) | D7: =XLOOKUP(A7,AssetData[Asset ID],AssetData[Salvage Value]) | E7: =XLOOKUP(A7,AssetData[Asset ID],AssetData[Useful Life]) | F7: =XLOOKUP(A7,AssetData[Asset ID],AssetData[Months in Service]) | G7: =SLN(C7,D7,E7) | H7: =DDB(C7,D7,E7,1) | I7: =G7*F7/12 | J7: =H7*F7/12 | K7: =C7-I7 | L7: =C7-J7

Sheet Method Comparison
A1: Method Comparison
A3: Asset ID | B3: Description | C3: Months | D3: SL Year 1 | E3: DDB Year 1 | F3: DDB Higher By | G3: SL End BV | H3: DDB End BV | I3: BV Difference | J3: Profit Signal
A4: A-001 | B4: ='Partial-Year Depreciation'!B4 | C4: ='Partial-Year Depreciation'!F4 | D4: ='Partial-Year Depreciation'!I4 | E4: ='Partial-Year Depreciation'!J4 | F4: =E4-D4 | G4: ='Partial-Year Depreciation'!K4 | H4: ='Partial-Year Depreciation'!L4 | I4: =H4-G4 | J4: =IF(F4>0,"DDB lowers Year 1 profit more","No acceleration impact")
A5: A-002 | B5: ='Partial-Year Depreciation'!B5 | C5: ='Partial-Year Depreciation'!F5 | D5: ='Partial-Year Depreciation'!I5 | E5: ='Partial-Year Depreciation'!J5 | F5: =E5-D5 | G5: ='Partial-Year Depreciation'!K5 | H5: ='Partial-Year Depreciation'!L5 | I5: =H5-G5 | J5: =IF(F5>0,"DDB lowers Year 1 profit more","No acceleration impact")
A6: A-003 | B6: ='Partial-Year Depreciation'!B6 | C6: ='Partial-Year Depreciation'!F6 | D6: ='Partial-Year Depreciation'!I6 | E6: ='Partial-Year Depreciation'!J6 | F6: =E6-D6 | G6: ='Partial-Year Depreciation'!K6 | H6: ='Partial-Year Depreciation'!L6 | I6: =H6-G6 | J6: =IF(F6>0,"DDB lowers Year 1 profit more","No acceleration impact")
A7: A-004 | B7: ='Partial-Year Depreciation'!B7 | C7: ='Partial-Year Depreciation'!F7 | D7: ='Partial-Year Depreciation'!I7 | E7: ='Partial-Year Depreciation'!J7 | F7: =E7-D7 | G7: ='Partial-Year Depreciation'!K7 | H7: ='Partial-Year Depreciation'!L7 | I7: =H7-G7 | J7: =IF(F7>0,"DDB lowers Year 1 profit more","No acceleration impact")
A8: TOTAL | D8: =SUM(D4:D7) | E8: =SUM(E4:E7) | F8: =SUM(F4:F7) | G8: =SUM(G4:G7) | H8: =SUM(H4:H7) | I8: =SUM(I4:I7) | J8: Use totals for statement evidence

Sheet Income Statement
A1: Income Statement
A3: Line Item | B3: Straight-Line | C3: DDB | D3: DDB Impact
A4: Sales Revenue | B4: =SUMIF(EntryData[Statement Line],A4,EntryData[Amount]) | C4: =B4 | D4: =C4-B4
A5: Service Revenue | B5: =SUMIF(EntryData[Statement Line],A5,EntryData[Amount]) | C5: =B5 | D5: =C5-B5
A6: Total Revenue | B6: =SUM(B4:B5) | C6: =SUM(C4:C5) | D6: =C6-B6
A7: Cost of Goods Sold | B7: =SUMIF(EntryData[Statement Line],A7,EntryData[Amount]) | C7: =B7 | D7: =C7-B7
A8: Gross Profit | B8: =B6-B7 | C8: =C6-C7 | D8: =C8-B8
A10: Payroll Expense | B10: =SUMIF(EntryData[Statement Line],A10,EntryData[Amount]) | C10: =B10 | D10: =C10-B10
A11: Rent Expense | B11: =SUMIF(EntryData[Statement Line],A11,EntryData[Amount]) | C11: =B11 | D11: =C11-B11
A12: Utilities Expense | B12: =SUMIF(EntryData[Statement Line],A12,EntryData[Amount]) | C12: =B12 | D12: =C12-B12
A13: Insurance Expense | B13: =SUMIF(EntryData[Statement Line],A13,EntryData[Amount]) | C13: =B13 | D13: =C13-B13
A14: Advertising Expense | B14: =SUMIF(EntryData[Statement Line],A14,EntryData[Amount]) | C14: =B14 | D14: =C14-B14
A15: Depreciation Expense | B15: ='Method Comparison'!D8 | C15: ='Method Comparison'!E8 | D15: =C15-B15
A16: Total Operating Expenses | B16: =SUM(B10:B15) | C16: =SUM(C10:C15) | D16: =C16-B16
A17: Operating Income | B17: =B8-B16 | C17: =C8-C16 | D17: =C17-B17
A19: Interest Expense | B19: =SUMIF(EntryData[Statement Line],A19,EntryData[Amount]) | C19: =B19 | D19: =C19-B19
A20: Net Income | B20: =B17-B19 | C20: =C17-C19 | D20: =C20-B20

Sheet Balance Sheet
A1: Balance Sheet
A3: Line Item | B3: Straight-Line | C3: DDB | D3: DDB Impact
A4: Cash | B4: =SUMIF(EntryData[Statement Line],A4,EntryData[Amount]) | C4: =B4 | D4: =C4-B4
A5: Accounts Receivable | B5: =SUMIF(EntryData[Statement Line],A5,EntryData[Amount]) | C5: =B5 | D5: =C5-B5
A6: Inventory | B6: =SUMIF(EntryData[Statement Line],A6,EntryData[Amount]) | C6: =B6 | D6: =C6-B6
A7: Supplies | B7: =SUMIF(EntryData[Statement Line],A7,EntryData[Amount]) | C7: =B7 | D7: =C7-B7
A8: Total Current Assets | B8: =SUM(B4:B7) | C8: =SUM(C4:C7) | D8: =C8-B8
A10: Fixed Assets at Cost | B10: =SUM(AssetData[Cost]) | C10: =B10 | D10: =C10-B10
A11: Less: Accumulated Depreciation | B11: =-'Income Statement'!B15 | C11: =-'Income Statement'!C15 | D11: =C11-B11
A12: Net Fixed Assets | B12: =B10+B11 | C12: =C10+C11 | D12: =C12-B12
A13: Total Assets | B13: =B8+B12 | C13: =C8+C12 | D13: =C13-B13
A15: Accounts Payable | B15: =SUMIF(EntryData[Statement Line],A15,EntryData[Amount]) | C15: =B15 | D15: =C15-B15
A16: Loan Payable | B16: =SUMIF(EntryData[Statement Line],A16,EntryData[Amount]) | C16: =B16 | D16: =C16-B16
A17: Total Liabilities | B17: =SUM(B15:B16) | C17: =SUM(C15:C16) | D17: =C17-B17
A19: Owner Capital | B19: =SUMIF(EntryData[Statement Line],A19,EntryData[Amount]) | C19: =B19 | D19: =C19-B19
A20: Current Net Income | B20: ='Income Statement'!B20 | C20: ='Income Statement'!C20 | D20: =C20-B20
A21: Total Equity | B21: =SUM(B19:B20) | C21: =SUM(C19:C20) | D21: =C21-B21
A22: Total Liabilities + Equity | B22: =B17+B21 | C22: =C17+C21 | D22: =C22-B22
A23: Balance Check | B23: =B13-B22 | C23: =C13-C22 | D23: =C23-B23

Sheet Recommendation Evidence
A1: Recommendation Evidence
A3: Evidence Question | B3: Workbook Value | C3: Where It Comes From | D3: Memo Use
A4: How much higher is DDB Year 1 depreciation? | B4: ='Income Statement'!D15 | C4: Income Statement | D4: Shows profit impact
A5: How much lower is DDB net income? | B5: ='Income Statement'!D20 | C5: Income Statement | D5: Supports income statement claim
A6: How much lower is DDB net fixed assets? | B6: ='Balance Sheet'!D12 | C6: Balance Sheet | D6: Supports balance sheet claim
A7: Do both balance sheets balance? | B7: =IF(AND('Balance Sheet'!B23=0,'Balance Sheet'!C23=0),"Yes","No") | C7: Balance Sheet | D7: Supports workbook reliability
A8: Which method do you recommend? | B8: Straight-line for smoother Year 1 reporting | C8: Your analysis | D8: State your claim
A9: Risk or limitation | B9: DDB may better match fast asset wear, but it lowers Year 1 profit sharply. | C9: Your analysis | D9: Name what the method does not show

Sheet Formula Reference
A1: Formula Reference
A3: Need | B3: Excel Syntax | C3: Purpose | D3: Student Reminder
A4: Lookup | B4: '=XLOOKUP(asset_id, AssetData[Asset ID], return_column) | C4: Pull asset data from the register | D4: Use links, not typed copies
A5: Straight-line full year | B5: '=SLN(cost, salvage, life) | C5: Calculate full-year SL depreciation | D5: Then multiply by months / 12
A6: DDB full year | B6: '=DDB(cost, salvage, life, 1) | C6: Calculate Year 1 DDB depreciation | D6: Then multiply by months / 12
A7: Category totals | B7: '=SUMIF(EntryData[Statement Line],"Sales Revenue",EntryData[Amount]) | C7: Pull categorized entries into statements | D7: Your categories must be correct first
A8: Operating income | B8: '=Gross Profit - Total Operating Expenses | C8: Income statement impact | D8: DDB usually lowers Year 1 income
A9: Net fixed assets | B9: '=Fixed Assets at Cost - Accumulated Depreciation | C9: Balance sheet impact | D9: Accumulated depreciation is a contra asset
A10: Balance check | B10: '=Total Assets - Total Liabilities and Equity | C10: Verify the balance sheet | D10: The check should equal 0

Sheet Submission Check
A1: Submission Check
A3: Done? | B3: Check | C3: Notes | D3: Teacher
A4: ☑ | B4: Entry Categories classifies every entry with a report, section, statement line, and reason.
A5: ☑ | B5: Asset Register has complete purchase dates, months in service, and depreciable base formulas.
A6: ☑ | B6: Partial-Year Depreciation uses XLOOKUP, SLN, DDB, and months / 12.
A7: ☑ | B7: Method Comparison shows SL vs DDB Year 1 expense and ending book value.
A8: ☑ | B8: Income Statement includes revenue, direct costs, operating expenses, depreciation, and net income.
A9: ☑ | B9: Balance Sheet includes current assets, fixed assets, accumulated depreciation, liabilities, equity, and a zero balance check.
A10: ☑ | B10: Recommendation Evidence includes at least two statement-based numbers.
