Workbook

Sheet ReadMe
A1: Unit 07 Lesson 07 - Inventory Project Rehearsal Workbook
A3: Purpose | B3: This shared workbook is the Lesson 07 dress rehearsal before groups move into their own Unit 07 inventory datasets in Lessons 08-10.
A4: Business | B4: TechStart Hardware - USB-C docking station inventory review for an investor update.
A5: Question | B5: Which inventory valuation method tells the clearest, most defensible story about profit, turnover, and inventory risk?
A6: Rehearsal Rule | B6: Everyone uses the same numbers today so the class can compare workbook quality, evidence chains, and recommendation clarity directly.
A8: Workbook Map
A9: ReadMe | B9: Business brief, workbook map, and project standard.
A10: Inputs | B10: Shared controls plus top-level totals used across the workbook.
A11: BeginningInventory | B11: Opening layer that starts goods available for sale.
A12: Purchases | B12: Dated purchase layers with rising unit costs.
A13: Sales | B13: Sales transactions plus the specific-ID assignment log.
A14: Valuation | B14: Layer-by-layer FIFO, LIFO, Weighted Average, and Specific ID math.
A15: MethodCompare | B15: Side-by-side COGS, ending inventory, gross margin, turnover, and days on hand.
A16: Checks | B16: Validation flags for SKU completeness, costs, balance, and workbook readiness.
A17: Dashboard | B17: Investor-facing KPI snapshot and method comparison charts.
A18: Recommendation | B18: Claim + evidence + risk statement tied to workbook numbers.
A21: Definition Of Done
A22: - | B22: All four methods reconcile so COGS + Ending Inventory = GAFS.
A23: - | B23: MethodCompare shows the tradeoff between profitability and turnover.
A24: - | B24: Dashboard links the selected method to a clean KPI snapshot.
A25: - | B25: Recommendation cites workbook numbers and names one risk or limitation.
A26: - | B26: Checks sheet has no remaining action flags before peer audit.

Sheet Inputs
A1: Controls And Shared Totals
A3: Workbook Controls
A4: Control | B4: Value | C4: Why It Matters
A5: Selected Method | B5: Weighted Average | C5: Controls the dashboard snapshot and recommendation lens.
A6: As Of Date | B6: =MAX(BeginningInventory!$D$5,Purchases!$D$5,Purchases!$D$6,Purchases!$D$7,Purchases!$D$8,Sales!$C$5,Sales!$C$6,Sales!$C$7) | C6: Latest transaction date in the rehearsal dataset.
A7: Total Units Sold | B7: =SUM(Sales!$D$5:$D$7) | C7: Used by every valuation method.
A8: Total Revenue | B8: =SUM(Sales!$F$5:$F$7) | C8: Common revenue base for gross margin analysis.
A9: GAFS Units | B9: =SUM(BeginningInventory!$E$5)+SUM(Purchases!$E$5:$E$8) | C9: Beginning units plus purchases.
A10: GAFS Cost | B10: =SUM(BeginningInventory!$G$5)+SUM(Purchases!$G$5:$G$8) | C10: Total cost available for sale.
A11: Beginning Inventory Cost | B11: =SUM(BeginningInventory!$G$5) | C11: Used for average inventory turnover math.
A13: Interpretation Notes
A14: Topic | B14: Note
A15: Cost pattern | B15: Purchase costs rise from $30.00 to $35.50, so method choice changes both profit and ending inventory.
A16: Physical reality | B16: Units are identical, which makes Weighted Average practical and Specific ID harder to scale.
A17: Audience | B17: Assume an investor wants numbers that can be traced quickly and defended clearly.

Sheet BeginningInventory
A1: Beginning Inventory Layer
A4: LotID | B4: SKU | C4: Item | D4: ReceiptDate | E4: Units | F4: UnitCost | G4: ExtendedCost | H4: StorageNote | I4: Notes
A5: Beg-01 | B5: TS-DOCK-01 | C5: USB-C Docking Station | D5: 2025-01-01 | E5: 50 | F5: 28 | G5: =E5*F5 | H5: Warehouse A | I5: Opening layer carried into January

Sheet Purchases
A1: Purchase Layers
A4: LotID | B4: PO | C4: SKU | D4: ReceiptDate | E4: Units | F4: UnitCost | G4: ExtendedCost | H4: Vendor | I4: Notes
A5: PO-101 | B5: PO-101 | C5: TS-DOCK-01 | D5: 2025-01-05 | E5: 40 | F5: 30 | G5: =E5*F5 | H5: Northwave | I5: First January replenishment
A6: PO-102 | B6: PO-102 | C6: TS-DOCK-01 | D6: 2025-01-12 | E6: 35 | F6: 32 | G6: =E6*F6 | H6: Northwave | I6: Costs continue to rise
A7: PO-103 | B7: PO-103 | C7: TS-DOCK-01 | D7: 2025-01-20 | E7: 45 | F7: 34 | G7: =E7*F7 | H7: Northwave | I7: Conference demand restock
A8: PO-104 | B8: PO-104 | C8: TS-DOCK-01 | D8: 2025-01-28 | E8: 30 | F8: 35.5 | G8: =E8*F8 | H8: Northwave | I8: Late-month replacement at highest cost

Sheet Sales
A1: Sales And Specific-ID Assignment Log
A4: SaleID | B4: SKU | C4: SaleDate | D4: UnitsSold | E4: UnitPrice | F4: Revenue | G4: Notes
A5: INV-201 | B5: TS-DOCK-01 | C5: 2025-01-09 | D5: 25 | E5: 54 | F5: =D5*E5 | G5: Starter bundle rollout
A6: INV-202 | B6: TS-DOCK-01 | C6: 2025-01-18 | D6: 40 | E6: 55 | F6: =D6*E6 | G6: Conference order
A7: INV-203 | B7: TS-DOCK-01 | C7: 2025-01-30 | D7: 50 | E7: 56 | F7: =D7*E7 | G7: Month-end install batch
A10: Specific ID Assignment Table
A11: SaleID | B11: LotID | C11: UnitsAssigned | D11: UnitCost | E11: ExtendedCost | F11: WhyThisLot
A12: INV-201 | B12: Beg-01 | C12: 10 | D12: 28 | E12: =C12*D12 | F12: Reserved units from opening stock
A13: INV-201 | B13: PO-101 | C13: 15 | D13: 30 | E13: =C13*D13 | F13: Paired with first restock
A14: INV-202 | B14: PO-101 | C14: 5 | D14: 30 | E14: =C14*D14 | F14: Used remaining early lot
A15: INV-202 | B15: PO-102 | C15: 20 | D15: 32 | E15: =C15*D15 | F15: Mid-month promotion bundle
A16: INV-202 | B16: PO-103 | C16: 15 | D16: 34 | E16: =C16*D16 | F16: Conference installation timing
A17: INV-203 | B17: Beg-01 | C17: 5 | D17: 28 | E17: =C17*D17 | F17: Legacy units still tagged to service plans
A18: INV-203 | B18: PO-102 | C18: 5 | D18: 32 | E18: =C18*D18 | F18: Balanced mix for large order
A19: INV-203 | B19: PO-103 | C19: 20 | D19: 34 | E19: =C19*D19 | F19: Recent units matched to bulk shipment
A20: INV-203 | B20: PO-104 | C20: 20 | D20: 35.5 | E20: =C20*D20 | F20: Newest units pulled for rush installation

Sheet Valuation
A1: Layer-By-Layer Valuation
A3: Shared Inputs
A4: Total Units Sold | B4: =Inputs!$B$7
A5: GAFS Units | B5: =Inputs!$B$9
A6: GAFS Cost | B6: =Inputs!$B$10
A7: Revenue | B7: =Inputs!$B$8
A9: LotID | B9: Source | C9: ReceiptDate | D9: UnitsAvailable | E9: UnitCost | F9: FIFO Units Sold | G9: FIFO COGS | H9: FIFO Ending Units | I9: FIFO Ending Cost | J9: LIFO Units Sold | K9: LIFO COGS | L9: LIFO Ending Units | M9: LIFO Ending Cost | N9: Specific ID Units Sold | O9: Specific ID COGS | P9: Specific ID Ending Units | Q9: Specific ID Ending Cost
A10: =BeginningInventory!$A$5 | B10: Beginning | C10: =BeginningInventory!$D$5 | D10: =BeginningInventory!$E$5 | E10: =BeginningInventory!$F$5 | F10: =MAX(0,MIN(D10,$B$4)) | G10: =F10*E10 | H10: =D10-F10 | I10: =H10*E10 | J10: =MAX(0,MIN(D10,$B$4-SUM($J$11:$J$14))) | K10: =J10*E10 | L10: =D10-J10 | M10: =L10*E10 | N10: =SUMIF(Sales!$B$12:$B$20,A10,Sales!$C$12:$C$20) | O10: =N10*E10 | P10: =D10-N10 | Q10: =P10*E10
A11: =Purchases!$A$5 | B11: Purchase | C11: =Purchases!$D$5 | D11: =Purchases!$E$5 | E11: =Purchases!$F$5 | F11: =MAX(0,MIN(D11,$B$4-SUM($F$10:F10))) | G11: =F11*E11 | H11: =D11-F11 | I11: =H11*E11 | J11: =MAX(0,MIN(D11,$B$4-SUM($J$12:$J$14))) | K11: =J11*E11 | L11: =D11-J11 | M11: =L11*E11 | N11: =SUMIF(Sales!$B$12:$B$20,A11,Sales!$C$12:$C$20) | O11: =N11*E11 | P11: =D11-N11 | Q11: =P11*E11
A12: =Purchases!$A$6 | B12: Purchase | C12: =Purchases!$D$6 | D12: =Purchases!$E$6 | E12: =Purchases!$F$6 | F12: =MAX(0,MIN(D12,$B$4-SUM($F$10:F11))) | G12: =F12*E12 | H12: =D12-F12 | I12: =H12*E12 | J12: =MAX(0,MIN(D12,$B$4-SUM($J$13:$J$14))) | K12: =J12*E12 | L12: =D12-J12 | M12: =L12*E12 | N12: =SUMIF(Sales!$B$12:$B$20,A12,Sales!$C$12:$C$20) | O12: =N12*E12 | P12: =D12-N12 | Q12: =P12*E12
A13: =Purchases!$A$7 | B13: Purchase | C13: =Purchases!$D$7 | D13: =Purchases!$E$7 | E13: =Purchases!$F$7 | F13: =MAX(0,MIN(D13,$B$4-SUM($F$10:F12))) | G13: =F13*E13 | H13: =D13-F13 | I13: =H13*E13 | J13: =MAX(0,MIN(D13,$B$4-SUM($J$14:$J$14))) | K13: =J13*E13 | L13: =D13-J13 | M13: =L13*E13 | N13: =SUMIF(Sales!$B$12:$B$20,A13,Sales!$C$12:$C$20) | O13: =N13*E13 | P13: =D13-N13 | Q13: =P13*E13
A14: =Purchases!$A$8 | B14: Purchase | C14: =Purchases!$D$8 | D14: =Purchases!$E$8 | E14: =Purchases!$F$8 | F14: =MAX(0,MIN(D14,$B$4-SUM($F$10:F13))) | G14: =F14*E14 | H14: =D14-F14 | I14: =H14*E14 | J14: =MAX(0,MIN(D14,$B$4)) | K14: =J14*E14 | L14: =D14-J14 | M14: =L14*E14 | N14: =SUMIF(Sales!$B$12:$B$20,A14,Sales!$C$12:$C$20) | O14: =N14*E14 | P14: =D14-N14 | Q14: =P14*E14
A17: Weighted Average Block
A18: Average Unit Cost | B18: =B6/B5
A19: Units Sold | B19: =B4
A20: Weighted Avg COGS | B20: =B18*B19
A21: Ending Units | B21: =B5-B19
A22: Weighted Avg Ending Inventory | B22: =B18*B21
A23: Balance Check | B23: =B20+B22

Sheet MethodCompare
A1: Method Comparison
A4: Method | B4: Units Sold | C4: Revenue | D4: COGS | E4: Ending Inventory | F4: Gross Margin $ | G4: Gross Margin % | H4: Avg Inventory | I4: Turnover | J4: Days On Hand | K4: Reading
A5: FIFO | B5: =Inputs!$B$7 | C5: =Inputs!$B$8 | D5: =SUM(Valuation!$G$10:$G$14) | E5: =SUM(Valuation!$I$10:$I$14) | F5: =C5-D5 | G5: =IFERROR(F5/C5,0) | H5: =(Inputs!$B$11+E5)/2 | I5: =IFERROR(D5/H5,0) | J5: =IFERROR(365/I5,0) | K5: Highest margin, slowest turnover
A6: LIFO | B6: =Inputs!$B$7 | C6: =Inputs!$B$8 | D6: =SUM(Valuation!$K$10:$K$14) | E6: =SUM(Valuation!$M$10:$M$14) | F6: =C6-D6 | G6: =IFERROR(F6/C6,0) | H6: =(Inputs!$B$11+E6)/2 | I6: =IFERROR(D6/H6,0) | J6: =IFERROR(365/I6,0) | K6: Lowest margin, fastest turnover
A7: Weighted Average | B7: =Inputs!$B$7 | C7: =Inputs!$B$8 | D7: =Valuation!$B$20 | E7: =Valuation!$B$22 | F7: =C7-D7 | G7: =IFERROR(F7/C7,0) | H7: =(Inputs!$B$11+E7)/2 | I7: =IFERROR(D7/H7,0) | J7: =IFERROR(365/I7,0) | K7: Balanced middle-ground view
A8: Specific ID | B8: =Inputs!$B$7 | C8: =Inputs!$B$8 | D8: =SUM(Valuation!$O$10:$O$14) | E8: =SUM(Valuation!$Q$10:$Q$14) | F8: =C8-D8 | G8: =IFERROR(F8/C8,0) | H8: =(Inputs!$B$11+E8)/2 | I8: =IFERROR(D8/H8,0) | J8: =IFERROR(365/I8,0) | K8: Precise but harder to scale
A11: Transfer Prompt
A12: If you had to defend one method in a project meeting, which row gives the clearest claim and what tradeoff would you have to explain?

Sheet Checks
A1: Validation And Readiness Checks
A4: Check | B4: What It Verifies | C4: Status | D4: Meaning
A5: Missing SKU | B5: Every data sheet has a SKU entered. | C5: =IF(COUNTBLANK(BeginningInventory!$B$5)+COUNTBLANK(Purchases!$C$5:$C$8)+COUNTBLANK(Sales!$B$5:$B$7)=0,"OK","Check SKU entry") | D5: Stops orphaned rows before totals roll up.
A6: Invalid Unit Cost | B6: No zero or negative purchase costs appear. | C6: =IF(COUNTIF(BeginningInventory!$F$5:$F$5,"<=0")+COUNTIF(Purchases!$F$5:$F$8,"<=0")=0,"OK","Invalid unit cost") | D6: Protects COGS and ending inventory math.
A7: Sales vs Supply | B7: Units sold do not exceed goods available. | C7: =IF(Inputs!$B$7<=Inputs!$B$9,"OK","Sales exceed supply") | D7: Prevents impossible inventory positions.
A8: FIFO Balance | B8: FIFO COGS + ending inventory = GAFS. | C8: =IF(ABS(SUM(Valuation!$G$10:$G$14)+SUM(Valuation!$I$10:$I$14)-Inputs!$B$10)<0.01,"OK","GAFS mismatch") | D8: Confirms FIFO layer math.
A9: LIFO Balance | B9: LIFO COGS + ending inventory = GAFS. | C9: =IF(ABS(SUM(Valuation!$K$10:$K$14)+SUM(Valuation!$M$10:$M$14)-Inputs!$B$10)<0.01,"OK","GAFS mismatch") | D9: Confirms LIFO layer math.
A10: Weighted Avg Balance | B10: Weighted Average totals reconcile. | C10: =IF(ABS(Valuation!$B$20+Valuation!$B$22-Inputs!$B$10)<0.01,"OK","GAFS mismatch") | D10: Confirms average-cost block.
A11: Specific ID Balance | B11: Specific ID totals reconcile to GAFS. | C11: =IF(ABS(SUM(Valuation!$O$10:$O$14)+SUM(Valuation!$Q$10:$Q$14)-Inputs!$B$10)<0.01,"OK","GAFS mismatch") | D11: Confirms assignment log ties back to cost layers.
A12: Assignment Total | B12: Specific ID assignments match units sold. | C12: =IF(SUM(Sales!$C$12:$C$20)=Inputs!$B$7,"OK","Assignment mismatch") | D12: Catches missing or duplicate lot assignments.
A13: Lot Capacity | B13: Specific ID assignments do not overuse any lot. | C13: =IF(MIN(Valuation!$P$10:$P$14)>=0,"OK","Lot over-assigned") | D13: Prevents negative units remaining.
A14: Dashboard Snapshot | B14: Dashboard selected-method cells are all linked. | C14: =IF(COUNTA(Dashboard!$C$4:$C$10)=7,"OK","Finish dashboard links") | D14: Prepares the workbook for investor reading.
A15: Recommendation Draft | B15: Recommendation has claim, evidence, comparison, risk, and final defense. | C15: =IF(AND(LEN(Recommendation!$B$7)>0,LEN(Recommendation!$B$8)>0,LEN(Recommendation!$B$9)>0,LEN(Recommendation!$B$10)>0,LEN(Recommendation!$B$11)>0,LEN(Recommendation!$B$12)>0),"OK","Finish recommendation") | D15: Confirms the evidence chain reaches the final claim.
A16: Date Freshness | B16: Transactions sit inside one active January window. | C16: =IF(MAX(BeginningInventory!$D$5,Purchases!$D$5,Purchases!$D$6,Purchases!$D$7,Purchases!$D$8,Sales!$C$5,Sales!$C$6,Sales!$C$7)-MIN(BeginningInventory!$D$5,Purchases!$D$5,Purchases!$D$6,Purchases!$D$7,Purchases!$D$8,Sales!$C$5,Sales!$C$6,Sales!$C$7)<=60,"OK","Check stale dates") | D16: Flags old dates before lessons 08-10 use new datasets.

Sheet Dashboard
A1: Investor Snapshot Dashboard
A3: Selected Method Snapshot
B4: Selected Method | C4: =Inputs!$B$5
B5: Revenue | C5: =INDEX(MethodCompare!$C$5:$C$8,MATCH(Inputs!$B$5,MethodCompare!$A$5:$A$8,0))
B6: COGS | C6: =INDEX(MethodCompare!$D$5:$D$8,MATCH(Inputs!$B$5,MethodCompare!$A$5:$A$8,0))
B7: Ending Inventory | C7: =INDEX(MethodCompare!$E$5:$E$8,MATCH(Inputs!$B$5,MethodCompare!$A$5:$A$8,0))
B8: Gross Margin % | C8: =INDEX(MethodCompare!$G$5:$G$8,MATCH(Inputs!$B$5,MethodCompare!$A$5:$A$8,0))
B9: Turnover | C9: =INDEX(MethodCompare!$I$5:$I$8,MATCH(Inputs!$B$5,MethodCompare!$A$5:$A$8,0))
B10: Days On Hand | C10: =INDEX(MethodCompare!$J$5:$J$8,MATCH(Inputs!$B$5,MethodCompare!$A$5:$A$8,0))
A12: Workbook Status
B13: Open Checks | C13: =COUNTIF(Checks!$C$5:$C$16,"<>OK")
B14: Peer Audit Ready? | C14: =IF(C13=0,"Yes","Not yet")
B15: Teacher Move | C15: Use the open checks to decide which weak spot gets fixed first.
B17: Student task | C17: Use INDEX/MATCH from MethodCompare so the selected method snapshot updates cleanly.

Sheet Recommendation
A1: Recommendation Sheet
A3: Claim + Evidence + Risk
A5: Recommended Method | B5: =Inputs!$B$5
A7: Claim | B7: Weighted Average is the most defensible method for this rehearsal because it balances profitability with a believable inventory story for identical products.
A8: Evidence 1 - Cost + ending inventory | B8: It produces COGS of $3,631.13 and ending inventory of $2,683.88, which keeps the workbook in balance with GAFS of $6,315.00.
A9: Evidence 2 - Turnover + days on hand | B9: Its gross margin is 42.8% with turnover of 1.78x and about 205.3 days on hand, giving TechStart a middle-ground operating picture.
A10: Comparison to another method | B10: Compared with FIFO's 46.5% gross margin and LIFO's 181.8 days on hand, Weighted Average avoids the highest-profit story without dropping to the lowest-margin position.
A11: Risk / Limitation | B11: Weighted Average smooths rising purchase costs, so managers may underreact to how quickly replacement costs are climbing.
A12: Final Recommendation | B12: Recommend Weighted Average for the rehearsal because the numbers are traceable, the method fits identical units, and the tradeoff story is easier to defend than Specific ID or an extreme FIFO/LIFO choice.
A14: Transfer reminder | B14: In Lessons 08-10, the sheet structure stays the same but your team must rebuild it with a different dataset and no teacher model.
