Workbook

Sheet Unadjusted TB
A1: Lesson 4 Manual Month-End Close
A2: Complete the March close in worksheet order. This is a separate practice case.
A4: Account | B4: Debit | C4: Credit
A5: Cash | B5: 9000 | C5: 0
A6: Accounts Receivable | B6: 4000 | C6: 0
A7: Supplies | B7: 5500 | C7: 0
A8: Prepaid Insurance | B8: 1200 | C8: 0
A9: Equipment | B9: 32000 | C9: 0
A10: Accumulated Depreciation | B10: 0 | C10: 0
A11: Accounts Payable | B11: 0 | C11: 6000
A12: Wages Payable | B12: 0 | C12: 0
A13: Unearned Revenue | B13: 0 | C13: 1200
A14: Retained Earnings | B14: 0 | C14: 30000
A15: Service Revenue | B15: 0 | C15: 14500
A16: Supplies Expense | B16: 0 | C16: 0
... A19: Wages Expense | B19: 0 | C19: 0
A20: Unadjusted totals | B20: =SUM(B5:B19) | C20: =SUM(C5:C19) | D20: =B20-C20
A23: Month-end facts
A24: Supplies on hand | B24: 4300
A25: Insurance policy length in months | B25: 4
A26: Insurance months used | B26: 1
A27: March equipment depreciation | B27: 400
A28: Wages earned but not paid | B28: 1800
A29: Advance service now complete | B29: 1200
A30: Completed work not yet billed | B30: 900
A32: Start values adapted from the current Lesson 5 TechStart starter.
A33: https://bodangren.github.io/Business-Operations/student/unit02/lesson05/#do

Sheet Adjustments
A1: Adjusting Entries
A2: Make six March 31 entries. Use one debit and one credit for each fact.
A4: Case | B4: Date | C4: Account | D4: Debit | E4: Credit
A5: 1 | B5: March 31
B6: March 31
A7: 2 | B7: March 31
B8: March 31
A9: 3 | B9: March 31
B10: March 31
A11: 4 | B11: March 31
B12: March 31
A13: 5 | B13: March 31
B14: March 31
A15: 6 | B15: March 31
B16: March 31
C18: Entry totals | D18: =SUM(D5:D16) | E18: =SUM(E5:E16)
C19: Debit less credit | D19: =D18-E18
C20: Check | D20: =IF(OR(COUNTA(C5:C16)<>12,COUNT(D5:E16)<>24),"Not finished",IF(D19=0,"Balanced","Review"))
A22: A zero difference does not prove that the accounts are correct.

Sheet Adjusted TB
A1: Adjusted Trial Balance
A2: Post the six entries. Calculate each adjusted account balance.
A4: Account | B4: Before Dr | C4: Before Cr | D4: Adjust Dr | E4: Adjust Cr | F4: After Dr | G4: After Cr
A5: ='Unadjusted TB'!A5 | B5: ='Unadjusted TB'!B5 | C5: ='Unadjusted TB'!C5
A6: ='Unadjusted TB'!A6 | B6: ='Unadjusted TB'!B6 | C6: ='Unadjusted TB'!C6
A7: ='Unadjusted TB'!A7 | B7: ='Unadjusted TB'!B7 | C7: ='Unadjusted TB'!C7
A8: ='Unadjusted TB'!A8 | B8: ='Unadjusted TB'!B8 | C8: ='Unadjusted TB'!C8
A9: ='Unadjusted TB'!A9 | B9: ='Unadjusted TB'!B9 | C9: ='Unadjusted TB'!C9
A10: ='Unadjusted TB'!A10 | B10: ='Unadjusted TB'!B10 | C10: ='Unadjusted TB'!C10
A11: ='Unadjusted TB'!A11 | B11: ='Unadjusted TB'!B11 | C11: ='Unadjusted TB'!C11
A12: ='Unadjusted TB'!A12 | B12: ='Unadjusted TB'!B12 | C12: ='Unadjusted TB'!C12
A13: ='Unadjusted TB'!A13 | B13: ='Unadjusted TB'!B13 | C13: ='Unadjusted TB'!C13
A14: ='Unadjusted TB'!A14 | B14: ='Unadjusted TB'!B14 | C14: ='Unadjusted TB'!C14
A15: ='Unadjusted TB'!A15 | B15: ='Unadjusted TB'!B15 | C15: ='Unadjusted TB'!C15
A16: ='Unadjusted TB'!A16 | B16: ='Unadjusted TB'!B16 | C16: ='Unadjusted TB'!C16
... A19: ='Unadjusted TB'!A19 | B19: ='Unadjusted TB'!B19 | C19: ='Unadjusted TB'!C19
A20: Totals | B20: =SUM(B5:B19) | C20: =SUM(C5:C19) | D20: =SUM(D5:D19) | E20: =SUM(E5:E19) | F20: =SUM(F5:F19) | G20: =SUM(G5:G19)
A21: Adjusted difference | F21: =IF(COUNT(D5:G19)<>60,"",F20-G20)
A22: Check entries and account balances before you make statements.

Sheet Financial Statements
A1: Financial Statements
A2: Use the adjusted trial balance. Complete the statements in order.
A4: Income Statement
A5: Service Revenue
A6: Supplies Expense
A7: Insurance Expense
A8: Depreciation Expense
A9: Wages Expense
A10: Total Expenses
A11: Net Income
A13: Statement of Retained Earnings
A14: Beginning Retained Earnings | B14: ='Unadjusted TB'!C14
A15: Net Income
A16: Ending Retained Earnings
A18: Balance Sheet
A19: Cash
A20: Accounts Receivable
A21: Supplies
A22: Prepaid Insurance
A23: Equipment
A24: Accumulated Depreciation (subtract)
A25: Total Assets
A27: Accounts Payable
A28: Wages Payable
... A33: Total Liabilities and Equity
A35: Balance Sheet difference | B35: =IF(COUNT(B25,B33)<2,"",B25-B33)
A37: Net Income moves to Retained Earnings. Ending Retained Earnings moves to the Balance Sheet.

Sheet Closing Entries
A1: Closing Entries
A2: Close revenue, expenses, and Income Summary after the statements.
A4: Step | B4: Date | C4: Account | D4: Debit | E4: Credit
A5: Close revenue | B5: March 31
B6: March 31
A7: Close expenses | B7: March 31
B8: March 31
B9: March 31
B10: March 31
B11: March 31
A12: Close Income Summary | B12: March 31
B13: March 31
C15: Closing totals | D15: =SUM(D5:D13) | E15: =SUM(E5:E13)
C16: Debit less credit | D16: =IF(OR(COUNTA(C5:C13)<>9,COUNT(D5:E13)<>18),"",D15-E15)
A19: Each temporary account must have a zero balance after closing.

Sheet Post-closing TB
A1: Post-closing Trial Balance
A2: Enter permanent accounts only. Carry forward their balances after closing.
A4: Account | B4: Debit | C4: Credit
A5: Cash
A6: Accounts Receivable
A7: Supplies
A8: Prepaid Insurance
A9: Equipment
A10: Accumulated Depreciation
A11: Accounts Payable
A12: Wages Payable
A13: Unearned Revenue
A14: Retained Earnings
A15: Post-closing totals | B15: =SUM(B5:B14) | C15: =SUM(C5:C14)
A16: Debit less credit | B16: =IF(COUNT(B5:C14)<>20,"",B15-C15)
A18: Do not include revenue, expense, or Income Summary accounts.
