Workbook

Sheet Transactions
A1: Transaction ID | B1: Date | C1: Description | D1: Account | E1: Type | F1: Debit | G1: Credit | H1: Entry Difference
A2: T001 | B2: 45660 | C2: Bakery website payment received | D2: Cash | E2: Asset | F2: 2200 | G2: 0 | H2: =SUMIFS(LedgerTable[Debit],LedgerTable[Transaction ID],[@[Transaction ID]])-SUMIFS(LedgerTable[Credit],LedgerTable[Transaction ID],[@[Transaction ID]])
A3: T001 | B3: 45660 | C3: Bakery website payment received | D3: Service Revenue | E3: Revenue | F3: 0 | G3: 2200 | H3: =SUMIFS(LedgerTable[Debit],LedgerTable[Transaction ID],[@[Transaction ID]])-SUMIFS(LedgerTable[Credit],LedgerTable[Transaction ID],[@[Transaction ID]])
A4: T002 | B4: 45663 | C4: Pet grooming social-media project billed | D4: Accounts Receivable | E4: Asset | F4: 650 | G4: 0 | H4: =SUMIFS(LedgerTable[Debit],LedgerTable[Transaction ID],[@[Transaction ID]])-SUMIFS(LedgerTable[Credit],LedgerTable[Transaction ID],[@[Transaction ID]])
A5: T002 | B5: 45663 | C5: Pet grooming social-media project billed | D5: Service Revenue | E5: Revenue | F5: 0 | G5: 650 | H5: =SUMIFS(LedgerTable[Debit],LedgerTable[Transaction ID],[@[Transaction ID]])-SUMIFS(LedgerTable[Credit],LedgerTable[Transaction ID],[@[Transaction ID]])
A6: T003 | B6: 45666 | C6: Advertising campaign paid | D6: Advertising Expense | E6: Expense | F6: 400 | G6: 0 | H6: =SUMIFS(LedgerTable[Debit],LedgerTable[Transaction ID],[@[Transaction ID]])-SUMIFS(LedgerTable[Credit],LedgerTable[Transaction ID],[@[Transaction ID]])
A7: T003 | B7: 45666 | C7: Advertising campaign paid | D7: Cash | E7: Asset | F7: 0 | G7: 400 | H7: =SUMIFS(LedgerTable[Debit],LedgerTable[Transaction ID],[@[Transaction ID]])-SUMIFS(LedgerTable[Credit],LedgerTable[Transaction ID],[@[Transaction ID]])
A8: T004 | B8: 45669 | C8: Adobe Creative Cloud subscription bought on account | D8: Software Subscription Expense | E8: Expense | F8: 52.99 | G8: 0 | H8: =SUMIFS(LedgerTable[Debit],LedgerTable[Transaction ID],[@[Transaction ID]])-SUMIFS(LedgerTable[Credit],LedgerTable[Transaction ID],[@[Transaction ID]])
A9: T004 | B9: 45669 | C9: Adobe Creative Cloud subscription bought on account | D9: Accounts Payable | E9: Liability | F9: 0 | G9: 52.99 | H9: =SUMIFS(LedgerTable[Debit],LedgerTable[Transaction ID],[@[Transaction ID]])-SUMIFS(LedgerTable[Credit],LedgerTable[Transaction ID],[@[Transaction ID]])
A10: T005 | B10: 45672 | C10: Dental office SEO payment received | D10: Cash | E10: Asset | F10: 1100 | G10: 0 | H10: =SUMIFS(LedgerTable[Debit],LedgerTable[Transaction ID],[@[Transaction ID]])-SUMIFS(LedgerTable[Credit],LedgerTable[Transaction ID],[@[Transaction ID]])
A11: T005 | B11: 45672 | C11: Dental office SEO payment received | D11: Service Revenue | E11: Revenue | F11: 0 | G11: 1100 | H11: =SUMIFS(LedgerTable[Debit],LedgerTable[Transaction ID],[@[Transaction ID]])-SUMIFS(LedgerTable[Credit],LedgerTable[Transaction ID],[@[Transaction ID]])
A12: T006 | B12: 45675 | C12: Adobe subscription balance paid | D12: Accounts Payable | E12: Liability | F12: 52.99 | G12: 0 | H12: =SUMIFS(LedgerTable[Debit],LedgerTable[Transaction ID],[@[Transaction ID]])-SUMIFS(LedgerTable[Credit],LedgerTable[Transaction ID],[@[Transaction ID]])
A13: T006 | B13: 45675 | C13: Adobe subscription balance paid | D13: Cash | E13: Asset | F13: 0 | G13: 52.99 | H13: =SUMIFS(LedgerTable[Debit],LedgerTable[Transaction ID],[@[Transaction ID]])-SUMIFS(LedgerTable[Credit],LedgerTable[Transaction ID],[@[Transaction ID]])
... A23: T011 | B23: 45687 | C23: Client invoice collected | D23: Accounts Receivable | E23: Asset | F23: 0 | G23: 900 | H23: =SUMIFS(LedgerTable[Debit],LedgerTable[Transaction ID],[@[Transaction ID]])-SUMIFS(LedgerTable[Credit],LedgerTable[Transaction ID],[@[Transaction ID]])

Sheet Trial Balance
A1: Account | B1: Total Debits | C1: Total Credits | D1: Debit Balance | E1: Credit Balance
A2: Cash | B2: =SUMIF(LedgerTable[Account],A2,LedgerTable[Debit]) | C2: =SUMIF(LedgerTable[Account],A2,LedgerTable[Credit]) | D2: =MAX(B2-C2,0) | E2: =MAX(C2-B2,0)
A3: Accounts Receivable | B3: =SUMIF(LedgerTable[Account],A3,LedgerTable[Debit]) | C3: =SUMIF(LedgerTable[Account],A3,LedgerTable[Credit]) | D3: =MAX(B3-C3,0) | E3: =MAX(C3-B3,0)
A4: Supplies Inventory | B4: =SUMIF(LedgerTable[Account],A4,LedgerTable[Debit]) | C4: =SUMIF(LedgerTable[Account],A4,LedgerTable[Credit]) | D4: =MAX(B4-C4,0) | E4: =MAX(C4-B4,0)
A5: Inventory | B5: =SUMIF(LedgerTable[Account],A5,LedgerTable[Debit]) | C5: =SUMIF(LedgerTable[Account],A5,LedgerTable[Credit]) | D5: =MAX(B5-C5,0) | E5: =MAX(C5-B5,0)
A6: Equipment | B6: =SUMIF(LedgerTable[Account],A6,LedgerTable[Debit]) | C6: =SUMIF(LedgerTable[Account],A6,LedgerTable[Credit]) | D6: =MAX(B6-C6,0) | E6: =MAX(C6-B6,0)
A7: Accounts Payable | B7: =SUMIF(LedgerTable[Account],A7,LedgerTable[Debit]) | C7: =SUMIF(LedgerTable[Account],A7,LedgerTable[Credit]) | D7: =MAX(B7-C7,0) | E7: =MAX(C7-B7,0)
A8: Notes Payable | B8: =SUMIF(LedgerTable[Account],A8,LedgerTable[Debit]) | C8: =SUMIF(LedgerTable[Account],A8,LedgerTable[Credit]) | D8: =MAX(B8-C8,0) | E8: =MAX(C8-B8,0)
A9: Unearned Revenue | B9: =SUMIF(LedgerTable[Account],A9,LedgerTable[Debit]) | C9: =SUMIF(LedgerTable[Account],A9,LedgerTable[Credit]) | D9: =MAX(B9-C9,0) | E9: =MAX(C9-B9,0)
A10: Owner's Capital | B10: =SUMIF(LedgerTable[Account],A10,LedgerTable[Debit]) | C10: =SUMIF(LedgerTable[Account],A10,LedgerTable[Credit]) | D10: =MAX(B10-C10,0) | E10: =MAX(C10-B10,0)
A11: Owner's Draw | B11: =SUMIF(LedgerTable[Account],A11,LedgerTable[Debit]) | C11: =SUMIF(LedgerTable[Account],A11,LedgerTable[Credit]) | D11: =MAX(B11-C11,0) | E11: =MAX(C11-B11,0)
A12: Service Revenue | B12: =SUMIF(LedgerTable[Account],A12,LedgerTable[Debit]) | C12: =SUMIF(LedgerTable[Account],A12,LedgerTable[Credit]) | D12: =MAX(B12-C12,0) | E12: =MAX(C12-B12,0)
A13: Sales Revenue | B13: =SUMIF(LedgerTable[Account],A13,LedgerTable[Debit]) | C13: =SUMIF(LedgerTable[Account],A13,LedgerTable[Credit]) | D13: =MAX(B13-C13,0) | E13: =MAX(C13-B13,0)
... A23: Utilities Expense | B23: =SUMIF(LedgerTable[Account],A23,LedgerTable[Debit]) | C23: =SUMIF(LedgerTable[Account],A23,LedgerTable[Credit]) | D23: =MAX(B23-C23,0) | E23: =MAX(C23-B23,0)
A24: Totals | B24: =SUM(B2:B23) | C24: =SUM(C2:C23) | D24: =SUM(D2:D23) | E24: =SUM(E2:E23)
A26: Difference | B26: =D24-E24
A27: Status | B27: =IF(ABS(B26)<0.01,"Balanced","Review Needed")

Sheet Error Checks
A1: Control | B1: Result | C1: Status | D1: Action if Review
A2: Ledger debit-credit difference | B2: =SUM(LedgerTable[Debit])-SUM(LedgerTable[Credit]) | C2: =IF(ABS(B2)<0.01,"Pass","Review") | D2: Find a missing or unequal amount.
A3: Rows in unbalanced transactions | B3: =COUNTIF(LedgerTable[Entry Difference],"<>0") | C3: =IF(ABS(B3)<0.01,"Pass","Review") | D3: Filter Entry Difference for nonzero values.
A4: Rows with a blank account | B4: =COUNTBLANK(LedgerTable[Account]) | C4: =IF(ABS(B4)<0.01,"Pass","Review") | D4: Complete each Account cell.
A5: Rows with both or neither amount | B5: =SUMPRODUCT(--((LedgerTable[Debit]=0)=(LedgerTable[Credit]=0))) | C5: =IF(ABS(B5)<0.01,"Pass","Review") | D5: Each row needs one debit or one credit.

Sheet Executive Summary
A1: TechStart Solutions Smart Ledger Summary
A2: Prepared By | B2: Student Team
A3: Total Debit Balances | B3: ='Trial Balance'!D24
A4: Total Credit Balances | B4: ='Trial Balance'!E24
A5: Difference | B5: ='Trial Balance'!B26
A6: Ledger Status | B6: ='Trial Balance'!B27
A7: Controls Needing Review | B7: =COUNTIF('Error Checks'!C2:C5,"Review")
A8: Revenue | B8: =SUMIFS(LedgerTable[Credit],LedgerTable[Type],"Revenue")-SUMIFS(LedgerTable[Debit],LedgerTable[Type],"Revenue")
A9: Expenses | B9: =SUMIFS(LedgerTable[Debit],LedgerTable[Type],"Expense")-SUMIFS(LedgerTable[Credit],LedgerTable[Type],"Expense")
A10: Net Income | B10: =B8-B9
A11: Cash Balance | B11: =SUMIF(LedgerTable[Account],"Cash",LedgerTable[Debit])-SUMIF(LedgerTable[Account],"Cash",LedgerTable[Credit])
A12: Recommendation | B12: TechStart can present the ledger because the controls pass and the business earned positive net income.
A13: Risk or Limitation | B13: The ledger covers one month. It does not prove that future revenue or cash flow will remain stable.
