Workbook

Sheet CostSetup
A1: Group 2 - Northside Print Lab Pricing Project
A2: Custom Hoodie Print Shop
A3: Classify each cost as Fixed or Variable in column C. The totals in column G feed every other sheet.
A5: Item | B5: Amount | C5: Category | D5: Notes | F5: Project Assumptions | G5: Value
A6: Shop rent | B6: 900 | C6: Fixed | D6: Monthly storefront rent | F6: Fixed Costs Total | G6: =SUMIF($C$6:$C$17,"Fixed",$B$6:$B$17) -> 2300
A7: Utilities base charge | B7: 180 | C7: Fixed | D7: Base utilities | F7: Variable Cost per Unit | G7: =SUMIF($C$6:$C$17,"Variable",$B$6:$B$17) -> 14
A8: Website storefront | B8: 70 | C8: Fixed | D8: Online ordering | F8: Monthly Capacity | G8: 220
A9: Equipment lease | B9: 450 | C9: Fixed | D9: Press and cutter | F9: Target Monthly Profit | G9: 500
A10: Insurance | B10: 140 | C10: Fixed | D10: General coverage | F10: Base Price | G10: 28
A11: Marketing retainer | B11: 220 | C11: Fixed | D11: Monthly ads | F11: Forecast Units @ Base Price | G11: 190
A12: Admin stipend | B12: 340 | C12: Fixed | D12: Part-time admin | F12: Suggested Price Band | G12: $24-$32 per hoodie
A13: Blank hoodie | B13: 8 | C13: Variable | D13: Per unit material
A14: Ink | B14: 1.75 | C14: Variable | D14: Per unit ink | F14: Option | G14: Price | H14: Forecast Units
A15: Packaging | B15: 0.75 | C15: Variable | D15: Per unit bag | F15: Bulk Spirit | G15: 24 | H15: 220
A16: Card fees | B16: 0.9 | C16: Variable | D16: Per unit processing | F16: Signature Hoodie | G16: 28 | H16: 190
A17: Print labor | B17: 2.6 | C17: Variable | D17: Per unit labor | F17: Premium Drop | G17: 32 | H17: 160

Sheet PriceOptions
A1: PriceOptions - Compare candidate prices
A2: Each option uses the same fixed and variable cost structure from CostSetup, but a different expected monthly demand.
A3: Fixed Costs | B3: =CostSetup!$G$6 -> 2300 | C3: Capacity | D3: =CostSetup!$G$8 -> 220
A4: Variable Cost per Unit | B4: =CostSetup!$G$7 -> 14
A6: Option | B6: Price | C6: Forecast Units | D6: Variable Cost | E6: CM ($) | F6: CM Ratio | G6: Projected Profit
A7: Bulk Spirit | B7: 24 | C7: 220 | D7: =CostSetup!$G$7 -> 14 | E7: =B7-D7 -> 10 | F7: =E7/B7 -> 0.4167 | G7: =(B7-D7)*C7-$B$3 -> -100
A8: Signature Hoodie | B8: 28 | C8: 190 | D8: =CostSetup!$G$7 -> 14 | E8: =B8-D8 -> 14 | F8: =E8/B8 -> 0.5 | G8: =(B8-D8)*C8-$B$3 -> 360
A9: Premium Drop | B9: 32 | C9: 160 | D9: =CostSetup!$G$7 -> 14 | E9: =B9-D9 -> 18 | F9: =E9/B9 -> 0.5625 | G9: =(B9-D9)*C9-$B$3 -> 580

Sheet Feasibility
A1: Feasibility - Break-even and capacity check
A2: This sheet asks two questions: Does each option beat break-even, and does forecast demand stay inside monthly capacity?
A3: Fixed Costs | B3: =CostSetup!$G$6 -> 2300 | C3: Capacity | D3: =CostSetup!$G$8 -> 220
A5: Option | B5: Forecast Units | C5: Break-Even Units | D5: Above Break-Even? | E5: Capacity OK? | F5: Forecast Cushion | G5: Projected Profit
A6: Bulk Spirit | B6: =PriceOptions!C7 -> 220 | C6: =ROUNDUP($B$3/(PriceOptions!E7),0) -> 230 | D6: =IF(B6>=C6,"Yes","No") -> No | E6: =IF(B6<=$D$3,"Yes","No") -> Yes | F6: =B6-C6 -> -10 | G6: =PriceOptions!G7 -> -100
A7: Signature Hoodie | B7: =PriceOptions!C8 -> 190 | C7: =ROUNDUP($B$3/(PriceOptions!E8),0) -> 165 | D7: =IF(B7>=C7,"Yes","No") -> Yes | E7: =IF(B7<=$D$3,"Yes","No") -> Yes | F7: =B7-C7 -> 25 | G7: =PriceOptions!G8 -> 360
A8: Premium Drop | B8: =PriceOptions!C9 -> 160 | C8: =ROUNDUP($B$3/(PriceOptions!E9),0) -> 128 | D8: =IF(B8>=C8,"Yes","No") -> Yes | E8: =IF(B8<=$D$3,"Yes","No") -> Yes | F8: =B8-C8 -> 32 | G8: =PriceOptions!G9 -> 580

Sheet TargetProfit
A1: TargetProfit - Reverse solve from the target
A2: Use the base price and base forecast from CostSetup to see what must change to hit the monthly target.
A3: Fixed Costs | B3: =CostSetup!$G$6 -> 2300
A4: Variable Cost per Unit | B4: =CostSetup!$G$7 -> 14
A5: Target Monthly Profit | B5: =CostSetup!$G$9 -> 500
A6: Base Price | B6: =CostSetup!$G$10 -> 28
A7: Base Forecast Units | B7: =CostSetup!$G$11 -> 190
A8: Capacity | B8: =CostSetup!$G$8 -> 220
A9: Contribution Margin @ Base Price | B9: =B6-B4 -> 14
A11: Required Units at Base Price | B11: =ROUNDUP((B3+B5)/B9,0) -> 200 | C11: Compare this to capacity
A12: Feasible at Capacity? | B12: =IF(B11<=B8,"Yes","No") -> Yes
A14: Required Price at Base Forecast | B14: =B4+((B3+B5)/B7) -> 28.74 | C14: Hold forecast units constant
A15: Price Change Needed | B15: =B14-B6 -> 0.74

Sheet PriceSensitivity
A1: PriceSensitivity - One-variable price scan
A2: Assumption: forecast volume stays at the base plan while price changes.
A3: Fixed Costs | B3: =CostSetup!$G$6 -> 2300
A4: Variable Cost per Unit | B4: =CostSetup!$G$7 -> 14
A5: Assumed Units | B5: =CostSetup!$G$11 -> 190
A7: Price | B7: Projected Profit
A8: 24 | B8: =(A8-$B$4)*$B$5-$B$3 -> -400
A9: 26 | B9: =(A9-$B$4)*$B$5-$B$3 -> -20
A10: 28 | B10: =(A10-$B$4)*$B$5-$B$3 -> 360
A11: 30 | B11: =(A11-$B$4)*$B$5-$B$3 -> 740
A12: 32 | B12: =(A12-$B$4)*$B$5-$B$3 -> 1120
A13: 34 | B13: =(A13-$B$4)*$B$5-$B$3 -> 1500

Sheet ProfitMatrix
A1: ProfitMatrix - Price and volume landscape
A2: This grid helps the team defend the recommendation during Q&A.
A3: Fixed Costs | B3: =CostSetup!$G$6 -> 2300 | C3: Variable Cost per Unit | D3: =CostSetup!$G$7 -> 14
A5: Price / Volume | B5: 140 | C5: 160 | D5: 180 | E5: 200 | F5: 220
A6: 24 | B6: =($A6-$D$3)*B$5-$B$3 -> -900 | C6: =($A6-$D$3)*C$5-$B$3 -> -700 | D6: =($A6-$D$3)*D$5-$B$3 -> -500 | E6: =($A6-$D$3)*E$5-$B$3 -> -300 | F6: =($A6-$D$3)*F$5-$B$3 -> -100
A7: 26 | B7: =($A7-$D$3)*B$5-$B$3 -> -620 | C7: =($A7-$D$3)*C$5-$B$3 -> -380 | D7: =($A7-$D$3)*D$5-$B$3 -> -140 | E7: =($A7-$D$3)*E$5-$B$3 -> 100 | F7: =($A7-$D$3)*F$5-$B$3 -> 340
A8: 28 | B8: =($A8-$D$3)*B$5-$B$3 -> -340 | C8: =($A8-$D$3)*C$5-$B$3 -> -60 | D8: =($A8-$D$3)*D$5-$B$3 -> 220 | E8: =($A8-$D$3)*E$5-$B$3 -> 500 | F8: =($A8-$D$3)*F$5-$B$3 -> 780
A9: 30 | B9: =($A9-$D$3)*B$5-$B$3 -> -60 | C9: =($A9-$D$3)*C$5-$B$3 -> 260 | D9: =($A9-$D$3)*D$5-$B$3 -> 580 | E9: =($A9-$D$3)*E$5-$B$3 -> 900 | F9: =($A9-$D$3)*F$5-$B$3 -> 1220
A10: 32 | B10: =($A10-$D$3)*B$5-$B$3 -> 220 | C10: =($A10-$D$3)*C$5-$B$3 -> 580 | D10: =($A10-$D$3)*D$5-$B$3 -> 940 | E10: =($A10-$D$3)*E$5-$B$3 -> 1300 | F10: =($A10-$D$3)*F$5-$B$3 -> 1660

Sheet Dashboard
A1: Dashboard - Final recommendation
A2: Choose one option and use the linked metrics below to defend the pricing decision.
A3: Recommended Option | B3: Premium Drop
A5: Metric | B5: Value
A6: Recommended Price | B6: =IF(B3="","",XLOOKUP(B3,PriceOptions!$A$7:$A$9,PriceOptions!$B$7:$B$9)) -> 32
A7: Forecast Units | B7: =IF(B3="","",XLOOKUP(B3,PriceOptions!$A$7:$A$9,PriceOptions!$C$7:$C$9)) -> 160
A8: Projected Profit | B8: =IF(B3="","",XLOOKUP(B3,PriceOptions!$A$7:$A$9,PriceOptions!$G$7:$G$9)) -> 580
A9: Break-Even Units | B9: =IF(B3="","",XLOOKUP(B3,Feasibility!$A$6:$A$8,Feasibility!$C$6:$C$8)) -> 128
A10: Target Met? | B10: =IF(B3="","",IF(B8>=CostSetup!$G$9,"Yes","No")) -> Yes
A11: Capacity OK? | B11: =IF(B3="","",XLOOKUP(B3,Feasibility!$A$6:$A$8,Feasibility!$E$6:$E$8)) -> Yes
A12: Downside Profit | B12: -400
A13: Upside Profit | B13: 1500
A15: Recommendation Statement | B15: Recommend Premium Drop at $32. It is the only listed package that clears the target profit while staying within the 220-hoodie monthly capacity.
A16: Risk Statement | B16: The premium option depends on at least 160 orders. If school demand weakens, the middle tier becomes the safer fallback.
A18: Option Summary
A19: Option | B19: Price | C19: Forecast Units | D19: Projected Profit
A20: Bulk Spirit | B20: 24 | C20: 220 | D20: -100
A21: Signature Hoodie | B21: 28 | C21: 190 | D21: 360
A22: Premium Drop | B22: 32 | C22: 160 | D22: 580
