Workbook

Sheet ReadMe
A1: Unit 07 Group 3 - Accessory Hub Inventory Starter Workbook
A3: Purpose | B3: This starter workbook extends the Lesson 07 rehearsal model. Use only Group 3's file and keep the sheet structure unchanged through Lessons 08-10.
A4: Business | B4: BrightCart Accessories - high-volume USB charging hub inventory with mostly stable unit costs.
A5: Question | B5: Which inventory method gives BrightCart the clearest recommendation when units are identical and costs stay in a narrow band?
A6: Rehearsal Rule | B6: Group 3 owns this workbook. Continue this same file across Lessons 08-10 and do not switch to another group's data.
A8: Workbook Map
A9: ReadMe | B9: Business brief, workbook map, and project standard.
A10: Inputs | B10: Shared controls plus top-level totals used across the workbook.
A11: BeginningInventory | B11: Opening layer that starts goods available for sale.
A12: Purchases | B12: Dated purchase layers with rising unit costs.
A13: Sales | B13: Sales transactions plus the specific-ID assignment log.
A14: Valuation | B14: Layer-by-layer FIFO, LIFO, Weighted Average, and Specific ID math.
A15: MethodCompare | B15: Side-by-side COGS, ending inventory, gross margin, turnover, and days on hand.
A16: Checks | B16: Validation flags for SKU completeness, costs, balance, and workbook readiness.
A17: Dashboard | B17: Investor-facing KPI snapshot and method comparison charts.
A18: Recommendation | B18: Claim + evidence + risk statement tied to workbook numbers.
A21: Definition Of Done
A22: - | B22: All four methods reconcile so COGS + Ending Inventory = GAFS.
A23: - | B23: MethodCompare shows the tradeoff between profitability and turnover.
A24: - | B24: Dashboard links the selected method to a clean KPI snapshot.
A25: - | B25: Recommendation cites workbook numbers and names one risk or limitation.
A26: - | B26: Checks sheet has no remaining action flags before peer audit.

Sheet Inputs
A1: Controls And Shared Totals
A3: Workbook Controls
A4: Control | B4: Value | C4: Why It Matters
A5: Selected Method | B5: Weighted Average | C5: Controls the dashboard snapshot and recommendation lens.
A6: As Of Date | B6: =MAX(BeginningInventory!$D$5,Purchases!$D$5,Purchases!$D$6,Purchases!$D$7,Purchases!$D$8,Sales!$C$5,Sales!$C$6,Sales!$C$7) | C6: Latest transaction date in the rehearsal dataset.
A7: Total Units Sold | B7: =SUM(Sales!$D$5:$D$7) | C7: Used by every valuation method.
A8: Total Revenue | B8: =SUM(Sales!$F$5:$F$7) | C8: Common revenue base for gross margin analysis.
A9: GAFS Units | B9: =SUM(BeginningInventory!$E$5)+SUM(Purchases!$E$5:$E$8) | C9: Beginning units plus purchases.
A10: GAFS Cost | B10: =SUM(BeginningInventory!$G$5)+SUM(Purchases!$G$5:$G$8) | C10: Total cost available for sale.
A11: Beginning Inventory Cost | B11: =SUM(BeginningInventory!$G$5) | C11: Used for average inventory turnover math.
A13: Interpretation Notes
A14: Topic | B14: Note
A15: Cost pattern | B15: Unit costs stay close together, so smoothing methods may tell the most practical story.
A16: Physical reality | B16: Charging hubs are identical retail units, so weighted-average logic is operationally realistic.
A17: Audience | B17: Assume a retail operations team wants a method that is easy to maintain and explain at scale.

Sheet BeginningInventory
A1: Beginning Inventory Layer
A4: LotID | B4: SKU | C4: Item | D4: ReceiptDate | E4: Units | F4: UnitCost | G4: ExtendedCost | H4: StorageNote | I4: Notes
A5: BC-BEG | B5: BC-HUB-02 | C5: USB Charging Hub | D5: 2025-01-01 | E5: 120 | F5: 18 | G5: =E5*F5 | H5: Aisle C | I5: Opening retail inventory

Sheet Purchases
A1: Purchase Layers
A4: LotID | B4: PO | C4: SKU | D4: ReceiptDate | E4: Units | F4: UnitCost | G4: ExtendedCost | H4: Vendor | I4: Notes
A5: BC-301 | B5: PO-301 | C5: BC-HUB-02 | D5: 2025-01-08 | E5: 80 | F5: 17.8 | G5: =E5*F5 | H5: RetailGrid | I5: Promo restock
A6: BC-302 | B6: PO-302 | C6: BC-HUB-02 | D6: 2025-01-19 | E6: 60 | F6: 18.2 | G6: =E6*F6 | H6: RetailGrid | I6: Standard replenishment
A7: BC-303 | B7: PO-303 | C7: BC-HUB-02 | D7: 2025-01-28 | E7: 90 | F7: 18.1 | G7: =E7*F7 | H7: RetailGrid | I7: Warehouse fill
A8: BC-304 | B8: PO-304 | C8: BC-HUB-02 | D8: 2025-02-09 | E8: 70 | F8: 17.9 | G8: =E8*F8 | H8: RetailGrid | I8: Late restock

Sheet Sales
A1: Sales And Specific-ID Assignment Log
A4: SaleID | B4: SKU | C4: SaleDate | D4: UnitsSold | E4: UnitPrice | F4: Revenue | G4: Notes
A5: INV-601 | B5: BC-HUB-02 | C5: 2025-01-14 | D5: 85 | E5: 32 | F5: =D5*E5 | G5: Marketplace promotion
A6: INV-602 | B6: BC-HUB-02 | C6: 2025-01-31 | D6: 90 | E6: 32.5 | F6: =D6*E6 | G6: Back-to-office order
A7: INV-603 | B7: BC-HUB-02 | C7: 2025-02-12 | D7: 70 | E7: 33 | F7: =D7*E7 | G7: Regional reseller shipment
A10: Specific ID Assignment Table
A11: SaleID | B11: LotID | C11: UnitsAssigned | D11: UnitCost | E11: ExtendedCost | F11: WhyThisLot
A12: INV-601 | B12: BC-BEG | C12: 40 | D12: 18 | E12: =C12*D12 | F12: Early shelf stock sold first
A13: INV-601 | B13: BC-301 | C13: 25 | D13: 17.8 | E13: =C13*D13 | F13: Promo lot blended into first wave
A14: INV-601 | B14: BC-302 | C14: 20 | D14: 18.2 | E14: =C14*D14 | F14: Standard replenishment units
A15: INV-602 | B15: BC-BEG | C15: 35 | D15: 18 | E15: =C15*D15 | F15: Remaining opening stock
A16: INV-602 | B16: BC-303 | C16: 30 | D16: 18.1 | E16: =C16*D16 | F16: Warehouse-fill lot
A17: INV-602 | B17: BC-304 | C17: 25 | D17: 17.9 | E17: =C17*D17 | F17: Late restock entered second wave
A18: INV-603 | B18: BC-BEG | C18: 15 | D18: 18 | E18: =C18*D18 | F18: Residual opening units
A19: INV-603 | B19: BC-301 | C19: 20 | D19: 17.8 | E19: =C19*D19 | F19: Promo lot carryover
A20: INV-603 | B20: BC-304 | C20: 35 | D20: 17.9 | E20: =C20*D20 | F20: Newest blended reseller shipment

Sheet Valuation
A1: Layer-By-Layer Valuation
A3: Shared Inputs
A4: Total Units Sold | B4: =Inputs!$B$7
A5: GAFS Units | B5: =Inputs!$B$9
A6: GAFS Cost | B6: =Inputs!$B$10
A7: Revenue | B7: =Inputs!$B$8
A9: LotID | B9: Source | C9: ReceiptDate | D9: UnitsAvailable | E9: UnitCost | F9: FIFO Units Sold | G9: FIFO COGS | H9: FIFO Ending Units | I9: FIFO Ending Cost | J9: LIFO Units Sold | K9: LIFO COGS | L9: LIFO Ending Units | M9: LIFO Ending Cost | N9: Specific ID Units Sold | O9: Specific ID COGS | P9: Specific ID Ending Units | Q9: Specific ID Ending Cost
A10: =BeginningInventory!$A$5 | B10: Beginning | C10: =BeginningInventory!$D$5 | D10: =BeginningInventory!$E$5 | E10: =BeginningInventory!$F$5 | F10: =MAX(0,MIN(D10,$B$4)) | G10: =F10*E10 | H10: =D10-F10 | I10: =H10*E10 | J10: =MAX(0,MIN(D10,$B$4-SUM($J$11:$J$14))) | K10: =J10*E10 | L10: =D10-J10 | M10: =L10*E10 | N10: =SUMIF(Sales!$B$12:$B$20,A10,Sales!$C$12:$C$20) | O10: =N10*E10 | P10: =D10-N10 | Q10: =P10*E10
A11: =Purchases!$A$5 | B11: Purchase | C11: =Purchases!$D$5 | D11: =Purchases!$E$5 | E11: =Purchases!$F$5 | F11: =MAX(0,MIN(D11,$B$4-SUM($F$10:F10))) | G11: =F11*E11 | H11: =D11-F11 | I11: =H11*E11 | J11: =MAX(0,MIN(D11,$B$4-SUM($J$12:$J$14))) | K11: =J11*E11 | L11: =D11-J11 | M11: =L11*E11 | N11: =SUMIF(Sales!$B$12:$B$20,A11,Sales!$C$12:$C$20) | O11: =N11*E11 | P11: =D11-N11 | Q11: =P11*E11
A12: =Purchases!$A$6 | B12: Purchase | C12: =Purchases!$D$6 | D12: =Purchases!$E$6 | E12: =Purchases!$F$6 | F12: =MAX(0,MIN(D12,$B$4-SUM($F$10:F11))) | G12: =F12*E12 | H12: =D12-F12 | I12: =H12*E12 | J12: =MAX(0,MIN(D12,$B$4-SUM($J$13:$J$14))) | K12: =J12*E12 | L12: =D12-J12 | M12: =L12*E12 | N12: =SUMIF(Sales!$B$12:$B$20,A12,Sales!$C$12:$C$20) | O12: =N12*E12 | P12: =D12-N12 | Q12: =P12*E12
A13: =Purchases!$A$7 | B13: Purchase | C13: =Purchases!$D$7 | D13: =Purchases!$E$7 | E13: =Purchases!$F$7 | F13: =MAX(0,MIN(D13,$B$4-SUM($F$10:F12))) | G13: =F13*E13 | H13: =D13-F13 | I13: =H13*E13 | J13: =MAX(0,MIN(D13,$B$4-SUM($J$14:$J$14))) | K13: =J13*E13 | L13: =D13-J13 | M13: =L13*E13 | N13: =SUMIF(Sales!$B$12:$B$20,A13,Sales!$C$12:$C$20) | O13: =N13*E13 | P13: =D13-N13 | Q13: =P13*E13
A14: =Purchases!$A$8 | B14: Purchase | C14: =Purchases!$D$8 | D14: =Purchases!$E$8 | E14: =Purchases!$F$8 | F14: =MAX(0,MIN(D14,$B$4-SUM($F$10:F13))) | G14: =F14*E14 | H14: =D14-F14 | I14: =H14*E14 | J14: =MAX(0,MIN(D14,$B$4)) | K14: =J14*E14 | L14: =D14-J14 | M14: =L14*E14 | N14: =SUMIF(Sales!$B$12:$B$20,A14,Sales!$C$12:$C$20) | O14: =N14*E14 | P14: =D14-N14 | Q14: =P14*E14
A17: Weighted Average Block
A18: Average Unit Cost | B18: =B6/B5
A19: Units Sold | B19: =B4
A20: Weighted Avg COGS | B20: =B18*B19
A21: Ending Units | B21: =B5-B19
A22: Weighted Avg Ending Inventory | B22: =B18*B21
A23: Balance Check | B23: =B20+B22

Sheet MethodCompare
A1: Method Comparison
A4: Method | B4: Units Sold | C4: Revenue | D4: COGS | E4: Ending Inventory | F4: Gross Margin $ | G4: Gross Margin % | H4: Avg Inventory | I4: Turnover | J4: Days On Hand | K4: Reading
A5: FIFO | B5: =Inputs!$B$7 | C5: =Inputs!$B$8 | D5: =SUM(Valuation!$G$10:$G$14) | E5: =SUM(Valuation!$I$10:$I$14) | F5: =C5-D5 | G5: =IFERROR(F5/C5,0) | H5: =(Inputs!$B$11+E5)/2 | I5: =IFERROR(D5/H5,0) | J5: =IFERROR(365/I5,0) | K5: Highest margin, slowest turnover
A6: LIFO | B6: =Inputs!$B$7 | C6: =Inputs!$B$8 | D6: =SUM(Valuation!$K$10:$K$14) | E6: =SUM(Valuation!$M$10:$M$14) | F6: =C6-D6 | G6: =IFERROR(F6/C6,0) | H6: =(Inputs!$B$11+E6)/2 | I6: =IFERROR(D6/H6,0) | J6: =IFERROR(365/I6,0) | K6: Lowest margin, fastest turnover
A7: Weighted Average | B7: =Inputs!$B$7 | C7: =Inputs!$B$8 | D7: =Valuation!$B$20 | E7: =Valuation!$B$22 | F7: =C7-D7 | G7: =IFERROR(F7/C7,0) | H7: =(Inputs!$B$11+E7)/2 | I7: =IFERROR(D7/H7,0) | J7: =IFERROR(365/I7,0) | K7: Balanced middle-ground view
A8: Specific ID | B8: =Inputs!$B$7 | C8: =Inputs!$B$8 | D8: =SUM(Valuation!$O$10:$O$14) | E8: =SUM(Valuation!$Q$10:$Q$14) | F8: =C8-D8 | G8: =IFERROR(F8/C8,0) | H8: =(Inputs!$B$11+E8)/2 | I8: =IFERROR(D8/H8,0) | J8: =IFERROR(365/I8,0) | K8: Precise but harder to scale
A11: Transfer Prompt
A12: If you had to defend one method in a project meeting, which row gives the clearest claim and what tradeoff would you have to explain?

Sheet Checks
A1: Validation And Readiness Checks
A4: Check | B4: What It Verifies | C4: Status | D4: Meaning
A5: Missing SKU | B5: Every data sheet has a SKU entered. | C5: =IF(COUNTBLANK(BeginningInventory!$B$5)+COUNTBLANK(Purchases!$C$5:$C$8)+COUNTBLANK(Sales!$B$5:$B$7)=0,"OK","Check SKU entry") | D5: Stops orphaned rows before totals roll up.
A6: Invalid Unit Cost | B6: No zero or negative purchase costs appear. | C6: =IF(COUNTIF(BeginningInventory!$F$5:$F$5,"<=0")+COUNTIF(Purchases!$F$5:$F$8,"<=0")=0,"OK","Invalid unit cost") | D6: Protects COGS and ending inventory math.
A7: Sales vs Supply | B7: Units sold do not exceed goods available. | C7: =IF(Inputs!$B$7<=Inputs!$B$9,"OK","Sales exceed supply") | D7: Prevents impossible inventory positions.
A8: FIFO Balance | B8: FIFO COGS + ending inventory = GAFS. | C8: =IF(ABS(SUM(Valuation!$G$10:$G$14)+SUM(Valuation!$I$10:$I$14)-Inputs!$B$10)<0.01,"OK","GAFS mismatch") | D8: Confirms FIFO layer math.
A9: LIFO Balance | B9: LIFO COGS + ending inventory = GAFS. | C9: =IF(ABS(SUM(Valuation!$K$10:$K$14)+SUM(Valuation!$M$10:$M$14)-Inputs!$B$10)<0.01,"OK","GAFS mismatch") | D9: Confirms LIFO layer math.
A10: Weighted Avg Balance | B10: Weighted Average totals reconcile. | C10: =IF(ABS(Valuation!$B$20+Valuation!$B$22-Inputs!$B$10)<0.01,"OK","GAFS mismatch") | D10: Confirms average-cost block.
A11: Specific ID Balance | B11: Specific ID totals reconcile to GAFS. | C11: =IF(ABS(SUM(Valuation!$O$10:$O$14)+SUM(Valuation!$Q$10:$Q$14)-Inputs!$B$10)<0.01,"OK","GAFS mismatch") | D11: Confirms assignment log ties back to cost layers.
A12: Assignment Total | B12: Specific ID assignments match units sold. | C12: =IF(SUM(Sales!$C$12:$C$20)=Inputs!$B$7,"OK","Assignment mismatch") | D12: Catches missing or duplicate lot assignments.
A13: Lot Capacity | B13: Specific ID assignments do not overuse any lot. | C13: =IF(MIN(Valuation!$P$10:$P$14)>=0,"OK","Lot over-assigned") | D13: Prevents negative units remaining.
A14: Dashboard Snapshot | B14: Dashboard selected-method cells are all linked. | C14: =IF(COUNTA(Dashboard!$C$4:$C$10)=7,"OK","Finish dashboard links") | D14: Prepares the workbook for investor reading.
A15: Recommendation Draft | B15: Recommendation has claim, evidence, comparison, risk, and final defense. | C15: =IF(AND(LEN(Recommendation!$B$7)>0,LEN(Recommendation!$B$8)>0,LEN(Recommendation!$B$9)>0,LEN(Recommendation!$B$10)>0,LEN(Recommendation!$B$11)>0,LEN(Recommendation!$B$12)>0),"OK","Finish recommendation") | D15: Confirms the evidence chain reaches the final claim.
A16: Date Freshness | B16: Transactions sit inside one active January window. | C16: =IF(MAX(BeginningInventory!$D$5,Purchases!$D$5,Purchases!$D$6,Purchases!$D$7,Purchases!$D$8,Sales!$C$5,Sales!$C$6,Sales!$C$7)-MIN(BeginningInventory!$D$5,Purchases!$D$5,Purchases!$D$6,Purchases!$D$7,Purchases!$D$8,Sales!$C$5,Sales!$C$6,Sales!$C$7)<=60,"OK","Check stale dates") | D16: Flags old dates before lessons 08-10 use new datasets.

Sheet Dashboard
A1: Investor Snapshot Dashboard
A3: Selected Method Snapshot
B4: Selected Method | C4: =Inputs!$B$5
B5: Revenue
B6: COGS
B7: Ending Inventory
B8: Gross Margin %
B9: Turnover
B10: Days On Hand
A12: Workbook Status
B13: Open Checks | C13: =COUNTIF(Checks!$C$5:$C$16,"<>OK")
B14: Peer Audit Ready? | C14: =IF(C13=0,"Yes","Not yet")
B15: Teacher Move | C15: Use the open checks to decide which weak spot gets fixed first.
B17: Student task | C17: Use INDEX/MATCH from MethodCompare so the selected method snapshot updates cleanly.

Sheet Recommendation
A1: Recommendation Sheet
A3: Claim + Evidence + Risk
A5: Recommended Method | B5: =Inputs!$B$5
A7: Claim
A8: Evidence 1 - Cost + ending inventory
A9: Evidence 2 - Turnover + days on hand
A10: Comparison to another method
A11: Risk / Limitation
A12: Final Recommendation
A14: Transfer reminder | B14: Use only this starter workbook for your group. Keep the Lesson 07 tab structure, finish the dashboard snapshot, and build the recommendation across Lessons 08-10.
