Workbook

Sheet Asset Register
A1: Partial-Year Asset Register - Teacher Key
A3: Asset ID | B3: Description | C3: Cost | D3: Salvage Value | E3: Useful Life | F3: Purchase Date | G3: Months in Service | H3: Depreciable Base
A4: A-001 | B4: Delivery Van | C4: 30000 | D4: 5000 | E4: 5 | F4: 4/1/2025 | G4: 9 | H4: =C4-D4
A5: A-002 | B5: Laptop Set | C5: 12000 | D5: 2000 | E5: 4 | F5: 7/1/2025 | G5: 6 | H5: =C5-D5
A6: A-003 | B6: Server Rack | C6: 8000 | D6: 800 | E6: 3 | F6: 10/1/2025 | G6: 3 | H6: =C6-D6
A9: Teacher key
A10: Completed key: formulas link from AssetData through partial-year depreciation, method comparison, and mini statements.

Sheet Partial-Year Depreciation
A1: Partial-Year Depreciation - Teacher Key
A3: Asset ID | B3: Description | C3: Cost | D3: Salvage | E3: Life | F3: Months | G3: SLN Full-Year | H3: DDB Full-Year | I3: SL Year 1 | J3: DDB Year 1 | K3: SL End BV | L3: DDB End BV | M3: Check
A4: A-001 | B4: =XLOOKUP($A4,AssetData[Asset ID],AssetData[Description],"") | C4: =XLOOKUP($A4,AssetData[Asset ID],AssetData[Cost],"") | D4: =XLOOKUP($A4,AssetData[Asset ID],AssetData[Salvage Value],"") | E4: =XLOOKUP($A4,AssetData[Asset ID],AssetData[Useful Life],"") | F4: =XLOOKUP($A4,AssetData[Asset ID],AssetData[Months in Service],"") | G4: =SLN(C4,D4,E4) | H4: =DDB(C4,D4,E4,1) | I4: =G4*F4/12 | J4: =H4*F4/12 | K4: =C4-I4 | L4: =C4-J4 | M4: =IF(AND(ROUND(K4,2)=ROUND(C4-I4,2),ROUND(L4,2)=ROUND(C4-J4,2)),"OK","ERROR")
A5: A-002 | B5: =XLOOKUP($A5,AssetData[Asset ID],AssetData[Description],"") | C5: =XLOOKUP($A5,AssetData[Asset ID],AssetData[Cost],"") | D5: =XLOOKUP($A5,AssetData[Asset ID],AssetData[Salvage Value],"") | E5: =XLOOKUP($A5,AssetData[Asset ID],AssetData[Useful Life],"") | F5: =XLOOKUP($A5,AssetData[Asset ID],AssetData[Months in Service],"") | G5: =SLN(C5,D5,E5) | H5: =DDB(C5,D5,E5,1) | I5: =G5*F5/12 | J5: =H5*F5/12 | K5: =C5-I5 | L5: =C5-J5 | M5: =IF(AND(ROUND(K5,2)=ROUND(C5-I5,2),ROUND(L5,2)=ROUND(C5-J5,2)),"OK","ERROR")
A6: A-003 | B6: =XLOOKUP($A6,AssetData[Asset ID],AssetData[Description],"") | C6: =XLOOKUP($A6,AssetData[Asset ID],AssetData[Cost],"") | D6: =XLOOKUP($A6,AssetData[Asset ID],AssetData[Salvage Value],"") | E6: =XLOOKUP($A6,AssetData[Asset ID],AssetData[Useful Life],"") | F6: =XLOOKUP($A6,AssetData[Asset ID],AssetData[Months in Service],"") | G6: =SLN(C6,D6,E6) | H6: =DDB(C6,D6,E6,1) | I6: =G6*F6/12 | J6: =H6*F6/12 | K6: =C6-I6 | L6: =C6-J6 | M6: =IF(AND(ROUND(K6,2)=ROUND(C6-I6,2),ROUND(L6,2)=ROUND(C6-J6,2)),"OK","ERROR")
A8: Required formula ideas
A9: Lookup asset fields from AssetData with XLOOKUP.
A10: SL Year 1 = SLN(cost, salvage, life) * months / 12.
A11: DDB Year 1 = DDB(cost, salvage, life, 1) * months / 12.
A12: Ending Book Value = Cost - Year 1 Depreciation.

Sheet Method Comparison
A1: Method Comparison - Teacher Key
A3: Asset ID | B3: Description | C3: Months | D3: SL Year 1 | E3: DDB Year 1 | F3: DDB Higher By | G3: SL End BV | H3: DDB End BV | I3: BV Difference | J3: Profit Signal
A4: A-001 | B4: =XLOOKUP($A4,'Partial-Year Depreciation'!$A$4:$A$6,'Partial-Year Depreciation'!$B$4:$B$6,"") | C4: =XLOOKUP($A4,'Partial-Year Depreciation'!$A$4:$A$6,'Partial-Year Depreciation'!$F$4:$F$6,"") | D4: =XLOOKUP($A4,'Partial-Year Depreciation'!$A$4:$A$6,'Partial-Year Depreciation'!$I$4:$I$6,"") | E4: =XLOOKUP($A4,'Partial-Year Depreciation'!$A$4:$A$6,'Partial-Year Depreciation'!$J$4:$J$6,"") | F4: =E4-D4 | G4: =XLOOKUP($A4,'Partial-Year Depreciation'!$A$4:$A$6,'Partial-Year Depreciation'!$K$4:$K$6,"") | H4: =XLOOKUP($A4,'Partial-Year Depreciation'!$A$4:$A$6,'Partial-Year Depreciation'!$L$4:$L$6,"") | I4: =H4-G4 | J4: =IF(F4>0,"SL reports higher Year 1 income","No DDB premium")
A5: A-002 | B5: =XLOOKUP($A5,'Partial-Year Depreciation'!$A$4:$A$6,'Partial-Year Depreciation'!$B$4:$B$6,"") | C5: =XLOOKUP($A5,'Partial-Year Depreciation'!$A$4:$A$6,'Partial-Year Depreciation'!$F$4:$F$6,"") | D5: =XLOOKUP($A5,'Partial-Year Depreciation'!$A$4:$A$6,'Partial-Year Depreciation'!$I$4:$I$6,"") | E5: =XLOOKUP($A5,'Partial-Year Depreciation'!$A$4:$A$6,'Partial-Year Depreciation'!$J$4:$J$6,"") | F5: =E5-D5 | G5: =XLOOKUP($A5,'Partial-Year Depreciation'!$A$4:$A$6,'Partial-Year Depreciation'!$K$4:$K$6,"") | H5: =XLOOKUP($A5,'Partial-Year Depreciation'!$A$4:$A$6,'Partial-Year Depreciation'!$L$4:$L$6,"") | I5: =H5-G5 | J5: =IF(F5>0,"SL reports higher Year 1 income","No DDB premium")
A6: A-003 | B6: =XLOOKUP($A6,'Partial-Year Depreciation'!$A$4:$A$6,'Partial-Year Depreciation'!$B$4:$B$6,"") | C6: =XLOOKUP($A6,'Partial-Year Depreciation'!$A$4:$A$6,'Partial-Year Depreciation'!$F$4:$F$6,"") | D6: =XLOOKUP($A6,'Partial-Year Depreciation'!$A$4:$A$6,'Partial-Year Depreciation'!$I$4:$I$6,"") | E6: =XLOOKUP($A6,'Partial-Year Depreciation'!$A$4:$A$6,'Partial-Year Depreciation'!$J$4:$J$6,"") | F6: =E6-D6 | G6: =XLOOKUP($A6,'Partial-Year Depreciation'!$A$4:$A$6,'Partial-Year Depreciation'!$K$4:$K$6,"") | H6: =XLOOKUP($A6,'Partial-Year Depreciation'!$A$4:$A$6,'Partial-Year Depreciation'!$L$4:$L$6,"") | I6: =H6-G6 | J6: =IF(F6>0,"SL reports higher Year 1 income","No DDB premium")

Sheet Mini Income Statement
A1: Mini Income Statement - Teacher Key
A3: Line Item | B3: Straight-Line | C3: DDB | D3: Difference
A4: Revenue | B4: 85000 | C4: 85000 | D4: =C4-B4
A5: Other Operating Expenses | B5: 45000 | C5: 45000 | D5: =C5-B5
A6: Depreciation Expense | B6: =SUM('Partial-Year Depreciation'!I4:I6) | C6: =SUM('Partial-Year Depreciation'!J4:J6) | D6: =C6-B6
A7: Operating Income | B7: =B4-B5-B6 | C7: =C4-C5-C6 | D7: =C7-B7

Sheet Mini Balance Sheet
A1: Mini Balance Sheet - Teacher Key
A3: Line Item | B3: Straight-Line | C3: DDB | D3: Difference
A4: Fixed Asset Cost | B4: =SUM(AssetData[Cost]) | C4: =SUM(AssetData[Cost]) | D4: =C4-B4
A5: Less: Accumulated Depreciation | B5: =-'Mini Income Statement'!B6 | C5: =-'Mini Income Statement'!C6 | D5: =C5-B5
A6: Net Book Value | B6: =B4+B5 | C6: =C4+C5 | D6: =C6-B6

Sheet Recommendation Evidence
A1: Recommendation Evidence - Teacher Key
A3: Evidence Question | B3: Workbook Value | C3: Where It Comes From | D3: Memo Use
A4: How much higher is DDB Year 1 depreciation? | B4: ='Mini Income Statement'!C6-'Mini Income Statement'!B6 | C4: Mini Income Statement | D4: Shows profit impact
A5: How much lower is DDB operating income? | B5: ='Mini Income Statement'!B7-'Mini Income Statement'!C7 | C5: Mini Income Statement | D5: Supports income statement claim
A6: How much lower is DDB net book value? | B6: ='Mini Balance Sheet'!B6-'Mini Balance Sheet'!C6 | C6: Mini Balance Sheet | D6: Supports balance sheet claim
A7: Which method do you recommend? | C7: Your analysis | D7: State your claim

Sheet Formula Reference
A1: Formula Reference
A3: Need | B3: Excel Syntax | C3: Purpose | D3: Student Reminder
A4: Lookup | B4: '=XLOOKUP(asset_id, AssetData[Asset ID], return_column) | C4: Pull asset data from the register | D4: Use links, not typed copies
A5: Straight-line full year | B5: '=SLN(cost, salvage, life) | C5: Calculate full-year SL depreciation | D5: Then multiply by months / 12
A6: DDB full year | B6: '=DDB(cost, salvage, life, 1) | C6: Calculate Year 1 DDB depreciation | D6: Then multiply by months / 12
A7: Partial-year factor | B7: '=months / 12 | C7: Prorate annual depreciation | D7: Use months in service
A8: Operating income | B8: '=Revenue - OtherOpEx - Depreciation | C8: Income statement impact | D8: DDB usually lowers Year 1 income
A9: Net book value | B9: '=Cost - AccumulatedDepreciation | C9: Balance sheet impact | D9: Year 1 accumulated depreciation equals Year 1 depreciation

Sheet Submission Check
A1: Submission Check - Teacher Key
A3: Done? | B3: Check | C3: Notes | D3: Teacher
A4: ☐ | B4: Asset Register has complete purchase dates and months in service.
A5: ☐ | B5: Partial-Year Depreciation uses XLOOKUP, SLN, DDB, and months / 12.
A6: ☐ | B6: Method Comparison shows SL vs DDB Year 1 expense and ending book value.
A7: ☐ | B7: Mini Income Statement links depreciation expense to operating income.
A8: ☐ | B8: Mini Balance Sheet links accumulated depreciation to net book value.
A9: ☐ | B9: Recommendation Evidence includes at least two statement-based numbers.
